{
    "id": "cit_book_genshoku_trees_2_p363_2b489ebd11aa5d26876f00e66888973c",
    "book_id": "book_genshoku_trees_2",
    "page": 363,
    "taxon_name": "学名索引 (363頁)",
    "scientific_name": null,
    "family": null,
    "data_icons": null,
    "photos": [],
    "figures": [],
    "page_type": "TEXT_PAGE",
    "rarity_stars": null,
    "type": "description",
    "microhabitats": null,
    "substrate_tags": null,
    "distribution_text": null,
    "phenology_text": null,
    "dublin_core": {
        "dc:source": "book_genshoku_trees_2 (p.363)",
        "dc:type": "Text"
    },
    "darwin_core": {
        "dwc:scientificName": null,
        "dwc:vernacularName": "学名索引 (363頁)",
        "dwc:occurrenceRemarks": "cornuta V 38\ncrenata V 34\n  ――var. nummularia V 34\ngeniculata V 33\ngoshiensis V 37\nintegra V 35\nlatifolia V 36\nleucoclada V 37\nmacropoda V 32\nmicrococca V 32\nopaca V 38\npedunculosa V 33\nrotunda V 36\nrugosa V 36\nserrata V 33\nsugeroki var. longipedunculata\n     V 34\nIllicium IV 83\n  religiosum IV 83\nIndigofera IV 247\n  decora IV 248\n  kirilowii IV 247\n  pseudo-tinctoria IV 247\nItea IV 159\n  japonica IV 159\n\nJ\n\nJacobinia V 193\n  carnea V 193\nJasminum V 169\n  nudiflorum V 169\n  odoratissimum V 169\nJatropha IV 268\n  podagrica IV 268\nJuglans IV 3\n  mandshurica IV 3\n  ――subsp. sieboldiana IV 3\n  nigra IV 3\n  regia IV 3\nJuniperus V 276\n  chinensis V 276\n  ――f. globosa V 279\n  ――var. kaizuka V 278\n  ――var. procumbens V 278\n  ――var. sargentii V 278\n\n  communis var. nipponica\n     V 280\n  conferta V 279\n  ――var. maritima V 280\n  rigida V 279\n\nK\n\nKadsura IV 82\n  japonica IV 82\nKalmia V 144\n  latifolia V 144\nKalopanax V 97\n  pictus V 97\nKandelia V 88\n  candel V 88\nKerria IV 230\n  japonica IV 230\nKeteleeria V 260\n  davidiana V 260\nKoelreuteria V 26\n  paniculata V 26\nKorthabella IV 69\n  japonica IV 69\n\nL\n\nLactuca V 211\n  linguaefolia V 211\nLagerstroemia V 79\n  indica V 79\n  subcostata var. hirtella V 79\nLantana V 183\n  camara V 183\n  hybrida V 183\nLarix V 244\n  gmelini V 244\n  leptolepis V 245\nLasianthus V 180\n  curtisii V 180\n  japonicus V 180\nLaurus IV 95\n  nobilis IV 95\nLavandula V 188\n  vera V 188\nLecythis V 87"
    }
}