{
    "id": "cit_book_genshoku_amphibians_reptiles_p172_e372267fdcaf26e39aed5a0fa4f74ba1",
    "book_id": "book_genshoku_amphibians_reptiles",
    "page": 172,
    "taxon_name": "アカマダラ (続き)",
    "scientific_name": "Dinodon rufozonatum rufozonatum (CANTOR, 1842)",
    "family": "ナミヘビ科",
    "data_icons": null,
    "photos": [],
    "figures": [],
    "page_type": "MIXED_RECORD",
    "rarity_stars": null,
    "type": "description",
    "microhabitats": null,
    "substrate_tags": null,
    "distribution_text": null,
    "phenology_text": null,
    "dublin_core": {
        "dc:source": "book_genshoku_amphibians_reptiles (p.172)",
        "dc:type": "Text"
    },
    "darwin_core": {
        "dwc:scientificName": "Lycodon rufozonatus",
        "dwc:vernacularName": "アカマダラ (続き)",
        "dwc:occurrenceRemarks": "ている．腹板は 185〜205枚，尾下板は 60〜82対．全長：70〜120cm．\n　対馬，朝鮮，満洲，中国，台湾などに分布し，対馬ではごく普通に見られる．平地や低山地の水辺を好み，カエル，魚，トカゲなどを捕食する．性質はかなり荒く，捕えるとよく咬みつく．卵生で，8〜10 月頃に 8〜10個の卵を産む．卵は長径 3cm，短径 1.5cm ぐらい．\n\n第20図．アカマダラの頭部；左から右へ背面，腹面および左側面．",
        "dwc:taxonConceptID": "gbif:2455592",
        "dwc:taxonomicStatus": "SYNONYM",
        "dwc:originalNameUsage": "Dinodon rufozonatum rufozonatum (CANTOR, 1842)",
        "dwc:family": "Colubridae",
        "dwc:nameAccordingTo": "book_genshoku_amphibians_reptiles"
    },
    "gbif_taxon_key": 2455592,
    "gbif_status": "SYNONYM",
    "gbif_accepted_name": "Lycodon rufozonatus",
    "gbif_accepted_key": 5223677,
    "gbif_family": "Colubridae",
    "gbif_match_type": "HIGHERRANK"
}