{
    "id": "cit_book_genshoku_trees_1_p193_44c29edb103a2872f519ad0c9a0fdaaa",
    "book_id": "book_genshoku_trees_1",
    "page": 193,
    "taxon_name": "P",
    "scientific_name": null,
    "family": null,
    "data_icons": null,
    "photos": [],
    "figures": [],
    "page_type": "INDEX_PAGE",
    "rarity_stars": null,
    "type": "description",
    "microhabitats": null,
    "substrate_tags": null,
    "distribution_text": null,
    "phenology_text": null,
    "dublin_core": {
        "dc:source": "book_genshoku_trees_1 (p.193)",
        "dc:type": "Text"
    },
    "darwin_core": {
        "dwc:scientificName": null,
        "dwc:vernacularName": "P",
        "dwc:occurrenceRemarks": "Pachysandra V 87\n  terminalis V 87\nPachystachys V 181\n  lutea V 181\nPaederia V 181\n  scandens V 181\nPaeonia IV 112\n  suffruticosa IV 112\n  --'Taiyoh' IV 113\n  --'Tamausagi' IV 113\n  --'Teikan' IV 114\n  --'Toshikama' IV 114\n  --'Yachiyotsubaki' IV 113\n  --'Hanadaijin' IV 114\n  --'Higurashi' IV 114\n  --'Hunkounishiki' IV 114\n  --'Huro' IV 112\n  --'How' IV 112\nPaliurus V 287\n  ramosissimus IV 287\nPandanus V 223\n  boninense V 223\nParabenzoin IV 121\n  praecox IV 120\n  trilobum IV 121\nParthenocissus V 52\n  tricuspidata V 52\nPasania IV 39\n  edulis IV 40\n  glabra IV 40\nPaulownia IV 292\n  tomentosa IV 292\nPentas IV 88\n  ameriana IV 88\nPersea IV 115\n  thunbergii IV 115\nPhiladelphus IV 152\n  coronarius V 83\n  lewisii V 219\n  satsumi IV 152\n  --var. nikoensis V 221\nPhillyrea V 220\n  angustifolia V 220\n  latifolia V 221\n  --f. spinosa V 221\nPhotinia IV 208\n  glabra IV 208\n  serrulata IV 211\n  --'Super Red Robin' IV 208\nPhyllostachys V 232\n  aurea V 242\n  bambusoides V 241\n  --f. castillonis V 239\n  --f. holochrysa V 241\n  heterocycla V 242\n  --f. pubescens V 242\n  nigra V 246\n  --f. henonis V 246\nPicea V 252\n  abies V 252\n  bicolor V 250\n  engelmannii V 252\n  glauca V 246\n  jezoensis V 249\n  --var. hondoensis V 249\n  koyamai V 252\n  maximowiczii V 250\n  polita V 248\n  sitchensis V 253\nPieris V 131\n  japonica V 131\nPilea V 180\n  cadierei V 180\nPimelea V 162\n  ferruginea V 162\nPinus V 236\n  armandii var. amamiana V 240\n  bungeana V 241\n  densiflora V 236\n  --var. umbraculifera V 236\n  --f. oculus-draconis V 236\n  koraiensis V 238\n  luchuensis V 238\n  palustris V 242\n  parviflora V 238\n  --var. pentaphylla V 240\n  pinaster V 243\n  pumila V 242\n  radiata V 244\n  rigida V 242\n  strobus V 239\n  sylvestris V 243\n  taeda V 242\n  thunbergii V 237\nPiper IV 110\n  kadsura IV 110\nPistacia IV 276\n  chinensis IV 276\nPithecellobium V 160\n  dulce V 160\nPittosporum V 9\n  tobira V 9\nPlatanus IV 144\n  acerifolia IV 144\n  occidentalis IV 144\n  orientalis IV 145\nPlatycarya IV 22\n  strobilacea IV 22\nPlatycodon IV 200\n  grandiflorum IV 200\nPoinciana V 227\n  gilliesii V 227\n  pulcherrima V 227"
    }
}