{
  "北海道": {
    "features": "亜寒帯から冷温帯の広大な原生林、湿原、火山帯。知床は世界自然遺産。流氷が育む豊かな海洋生態系",
    "endemic_or_notable": "シマフクロウ、タンチョウ、エゾシカ、釧路湿原のヤチボウズ、大雪山のナキウサギ",
    "biodiversity_note": "本州とは異なるヒグマ・エゾリスなどの北方系動物相。ブラキストン線が生物地理の境界",
    "threats": "エゾシカの増加による森林植生への食害、外来種（アライグマ、セイヨウオオマルハナバチ）の拡大",
    "conservation": "知床世界自然遺産、釧路湿原ラムサール条約登録湿地、大雪山国立公園が30by30に貢献"
  },
  "青森県": {
    "features": "白神山地のブナ原生林、十和田湖・奥入瀬渓流、津軽海峡を挟んで北海道の生物相との接点",
    "endemic_or_notable": "白神山地のブナ林（世界遺産）、クマゲラ、ニホンカモシカ",
    "biodiversity_note": "ブナ林の林床にはギフチョウの食草ウスバサイシンが生育。冬季はハクチョウの越冬地として有名",
    "threats": "ブナ林へのナラ枯れの脅威、マタギ文化の衰退に伴う里山管理の低下",
    "conservation": "白神山地世界自然遺産の核心地域は人手を入れない保全方針。十和田八幡平国立公園"
  },
  "岩手県": {
    "features": "北上山地と奥羽山脈に挟まれた広大な県土。三陸海岸のリアス式地形が多様な海洋環境を形成",
    "endemic_or_notable": "早池峰山の固有植物（ハヤチネウスユキソウ）、三陸の海鳥繁殖地",
    "biodiversity_note": "ツキノワグマの高密度生息地。北上川流域の湿地にはサクラマスが遡上",
    "threats": "鹿の食害拡大、松枯れによる海岸林の衰退",
    "conservation": "早池峰国定公園、三陸復興国立公園。震災後の自然再生が進む"
  },
  "宮城県": {
    "features": "蔵王連峰から仙台平野、松島湾の多島海まで変化に富む地形。伊豆沼は国際的な渡り鳥の中継地",
    "endemic_or_notable": "伊豆沼のマガン・ヒシクイ飛来地、蔵王のアオモリトドマツ樹氷林",
    "biodiversity_note": "伊豆沼には毎冬数万羽のガンカモ類が飛来。仙台市内でもオオタカが営巣",
    "threats": "松島湾の水質悪化、沿岸開発による干潟の減少、震災後の地盤沈下で生じた湿地の管理",
    "conservation": "伊豆沼・内沼ラムサール条約登録湿地、栗駒国定公園"
  },
  "秋田県": {
    "features": "白神山地の東側、十和田湖南部、鳥海山の高山帯。豊富な降雪が独特のブナ林生態系を育む",
    "endemic_or_notable": "森吉山のクマゲラ営巣地、八郎潟干拓地の野鳥、鳥海山の高山植物",
    "biodiversity_note": "日本海側の多雪環境に適応した植物群落。マタギ文化が残る地域ではツキノワグマとの共存の知恵が継承",
    "threats": "過疎化に伴う里山・水田の放棄、ナラ枯れの拡大",
    "conservation": "白神山地世界遺産の秋田側、十和田八幡平国立公園、鳥海国定公園"
  },
  "山形県": {
    "features": "月山・出羽三山の山岳信仰の森、最上川流域の河畔林、庄内平野の水田地帯",
    "endemic_or_notable": "月山の高山植物帯、飛島の海鳥繁殖地、朝日連峰のイヌワシ",
    "biodiversity_note": "出羽三山の社寺林は数百年の老齢林。庄内平野ではハクチョウとガンの混群が冬季に見られる",
    "threats": "ブナ林のナラ枯れ、河川改修による氾濫原湿地の減少",
    "conservation": "磐梯朝日国立公園、出羽三山の信仰の森が事実上の保護林として機能"
  },
  "福島県": {
    "features": "会津の山地から中通りの盆地、浜通りの太平洋岸まで三地域で気候・植生が大きく異なる",
    "endemic_or_notable": "尾瀬の高層湿原（ミズバショウ群落）、裏磐梯の湖沼群、只見のブナ林",
    "biodiversity_note": "尾瀬は日本を代表する高層湿原で多数の湿原性植物が生育。帰還困難区域では人の不在により野生動物が回復",
    "threats": "原発事故による長期避難地域の管理放棄、イノシシの爆発的増加",
    "conservation": "尾瀬国立公園、磐梯朝日国立公園、只見ユネスコエコパーク"
  },
  "茨城県": {
    "features": "関東平野北東部の平坦な地形。霞ヶ浦は日本第2位の湖沼面積を持つ",
    "endemic_or_notable": "霞ヶ浦の水生生物、筑波山の暖温帯・冷温帯の植生境界",
    "biodiversity_note": "霞ヶ浦には多くの淡水魚が生息するが外来種の影響が大きい。筑波山では標高800m足らずでブナが出現する南限域",
    "threats": "霞ヶ浦の富栄養化と外来魚（ブラックバス・ブルーギル）、平地林の開発",
    "conservation": "霞ヶ浦の水質改善事業、筑波山地域ジオパーク"
  },
  "栃木県": {
    "features": "日光連山の亜高山帯から関東平野北端の平地まで。中禅寺湖は標高1269mの高所湖沼",
    "endemic_or_notable": "日光のニホンザル（国際的に著名な研究対象）、奥日光の湿原、戦場ヶ原のラムサール候補地",
    "biodiversity_note": "日光の社寺林はスギの巨木林。渡良瀬遊水地はコウノトリの野生復帰拠点",
    "threats": "ニホンジカの食害による日光の森林・湿原の劣化が深刻",
    "conservation": "日光国立公園、渡良瀬遊水地ラムサール条約登録湿地"
  },
  "群馬県": {
    "features": "上毛三山（赤城・榛名・妙義）と尾瀬、利根川源流域。内陸性気候で夏暑く冬は乾燥",
    "endemic_or_notable": "尾瀬（群馬側）、谷川岳の高山植物、赤城山のアカヤシオ",
    "biodiversity_note": "利根川源流域は首都圏の水源であり同時に豊かな渓流生態系。クマタカが奥山に生息",
    "threats": "スキー場開発による高山植生への影響、ツキノワグマの人里出没",
    "conservation": "尾瀬国立公園（群馬側）、上信越高原国立公園"
  },
  "埼玉県": {
    "features": "関東平野の中央に位置し、秩父山地から大宮台地まで。荒川流域に広がる水田と河川敷",
    "endemic_or_notable": "秩父のニホンカモシカ、見沼田んぼの都市近郊湿地、三富新田の平地林",
    "biodiversity_note": "都市化が進む一方、荒川河川敷にはサギ類のコロニーが残る。秩父ではクマタカやイヌワシの記録も",
    "threats": "市街地拡大による農地・緑地の減少、荒川の河川敷樹林化",
    "conservation": "秩父多摩甲斐国立公園（埼玉側）、見沼田んぼの保全地域指定"
  },
  "千葉県": {
    "features": "三方を海に囲まれた半島。九十九里浜の砂浜海岸と東京湾岸の干潟。内陸は房総丘陵の照葉樹林",
    "endemic_or_notable": "谷津干潟のシギ・チドリ、房総の照葉樹林、東京湾のアマモ場再生",
    "biodiversity_note": "谷津干潟は都市の中に残る貴重な干潟。房総半島南部では暖流の影響で南方系の生物が北上",
    "threats": "東京湾の埋立による干潟・浅海域の消失、砂浜の侵食",
    "conservation": "谷津干潟ラムサール条約登録湿地、南房総国定公園"
  },
  "東京都": {
    "features": "世界最大級の都市圏でありながら奥多摩の山林や伊豆・小笠原諸島まで多様な環境を包含",
    "endemic_or_notable": "小笠原の固有種（メグロ、オガサワラオオコウモリ）、明治神宮の人工林が100年で天然林化",
    "biodiversity_note": "皇居・明治神宮など大規模緑地が都心の生物多様性を支える。多摩川ではアユが遡上回復",
    "threats": "ヒートアイランド現象、小笠原でのグリーンアノール等外来種の脅威",
    "conservation": "小笠原諸島世界自然遺産、秩父多摩甲斐国立公園、国民公園（皇居・新宿御苑）"
  },
  "神奈川県": {
    "features": "丹沢山系の落葉広葉樹林から湘南の海岸線まで多様な環境。相模湾は暖流の影響で南方系の生物も",
    "endemic_or_notable": "丹沢のブナ林、箱根の温泉生態系、三浦半島の照葉樹林",
    "biodiversity_note": "都市部でも緑地が残り、カワセミやタヌキが身近に生息。江の島はウミネコの繁殖地",
    "threats": "シカの食害による丹沢の植生劣化、都市化による湿地の減少",
    "conservation": "丹沢大山国定公園、県立自然環境保全地域が30by30に貢献"
  },
  "新潟県": {
    "features": "日本海側の豪雪地帯。越後平野の広大な水田地帯と佐渡島。信濃川・阿賀野川の大河川",
    "endemic_or_notable": "トキの野生復帰（佐渡）、福島潟のオオヒシクイ、瓢湖のハクチョウ",
    "biodiversity_note": "佐渡でのトキ放鳥は日本の希少種保全の象徴。豪雪がもたらす雪解け水が豊かな水田生態系を支える",
    "threats": "水田の耕作放棄、中山間地域の過疎化、海岸侵食",
    "conservation": "佐渡ジオパーク、瓢湖ラムサール条約登録湿地、トキの野生復帰事業"
  },
  "富山県": {
    "features": "立山連峰の3000m級高山から富山湾の深海まで、標高差4000m以上の垂直変化。立山の雪渓は万年雪",
    "endemic_or_notable": "立山のライチョウ、ホタルイカの群遊海面、黒部峡谷の原生林",
    "biodiversity_note": "富山湾は大陸棚が狭く深海が近いため、深海生物が沿岸で見られる特異な海域",
    "threats": "ライチョウの個体数減少（温暖化・捕食者の高標高進出）、スギ人工林の管理不足",
    "conservation": "中部山岳国立公園、立山のライチョウ保護事業"
  },
  "石川県": {
    "features": "能登半島の里海・里山と白山の高山帯。能登の棚田は生物多様性の宝庫",
    "endemic_or_notable": "白山の高山植物（ハクサンコザクラ等多数の白山冠種）、能登の里山里海（世界農業遺産）",
    "biodiversity_note": "能登の里山里海はFAO世界農業遺産に認定。伝統的な農林漁業が生物多様性を維持してきた好例",
    "threats": "能登の過疎化と里山管理の担い手不足、白山の高山植生への温暖化影響",
    "conservation": "白山国立公園、能登の里山里海世界農業遺産、加賀海岸国定公園"
  },
  "福井県": {
    "features": "若狭湾のリアス式海岸と越前海岸の断崖。奥越の豪雪地帯にはブナの原生林",
    "endemic_or_notable": "三方五湖の年縞堆積物（世界的な年代測定基準）、越前海岸のスイセン群落",
    "biodiversity_note": "三方五湖は淡水から汽水まで塩分濃度の異なる5つの湖が隣接し、多様な水生生物が生息",
    "threats": "原発立地による沿岸生態系への懸念、中山間地の耕作放棄",
    "conservation": "三方五湖ラムサール条約登録湿地、若狭湾国定公園"
  },
  "山梨県": {
    "features": "富士山北麓の溶岩台地と青木ヶ原樹海、南アルプスの高山帯、甲府盆地の果樹園",
    "endemic_or_notable": "富士山の垂直分布帯、青木ヶ原の溶岩洞窟性コウモリ、南アルプスのキタダケソウ",
    "biodiversity_note": "富士山は標高に沿って亜熱帯から亜高山帯まで植生帯が凝縮。南アルプスのキタダケソウは日本固有種",
    "threats": "富士山の入山者増加による踏圧、シカの食害、ナラ枯れ",
    "conservation": "富士箱根伊豆国立公園、南アルプス国立公園、南アルプスユネスコエコパーク"
  },
  "長野県": {
    "features": "日本アルプス3山脈が走り、高山帯から亜高山帯の自然が広がる。内陸性気候で寒暖差が大きい",
    "endemic_or_notable": "上高地のニホンザル（温泉入浴で有名）、志賀高原の湿原、霧ヶ峰のニッコウキスゲ",
    "biodiversity_note": "日本の屋根と呼ばれる山岳地帯にライチョウ・オコジョ・イワヒバリなどの高山性動物が生息",
    "threats": "高山帯への温暖化の影響、シカの分布拡大による亜高山帯への食害",
    "conservation": "中部山岳国立公園、南アルプス国立公園、上信越高原国立公園、志賀高原ユネスコエコパーク"
  },
  "岐阜県": {
    "features": "飛騨の山岳地帯から美濃の平野まで。長良川の清流は鵜飼で有名。白川郷の合掌造り集落周辺に豊かな里山",
    "endemic_or_notable": "長良川のアユ、白山のイヌワシ、飛騨の原生林",
    "biodiversity_note": "長良川は日本三大清流の一つで河口堰問題を経て水環境保全の象徴。オオサンショウウオが生息",
    "threats": "長良川河口堰による汽水域生態系への影響、中山間地の獣害",
    "conservation": "白山国立公園（岐阜側）、飛騨木曽川国定公園"
  },
  "静岡県": {
    "features": "富士山南麓から伊豆半島、駿河湾の深海まで。暖流の影響で温暖な気候。茶畑の景観",
    "endemic_or_notable": "富士山の植生帯、駿河湾の深海生物、浮島ヶ原の湿地植物",
    "biodiversity_note": "駿河湾は水深2500mと日本最深の湾。伊豆半島はフィリピン海プレート上で本州と異なる地質・生物相を持つ",
    "threats": "伊豆の開発圧、海岸侵食による砂浜の減少、富士山の環境負荷",
    "conservation": "富士箱根伊豆国立公園、南アルプス国立公園（静岡側）、伊豆半島ジオパーク"
  },
  "愛知県": {
    "features": "濃尾平野から知多・渥美半島の沿岸部、三河山間部まで。藤前干潟は名古屋港内に残る貴重な干潟",
    "endemic_or_notable": "藤前干潟のシギ・チドリ、東三河のホトケドジョウ、渥美半島のアカウミガメ産卵地",
    "biodiversity_note": "藤前干潟は都市内の干潟として国際的に貴重。矢作川流域にはオオサンショウウオが生息",
    "threats": "名古屋圏の都市拡大、伊勢湾の水質悪化、外来種の侵入",
    "conservation": "藤前干潟ラムサール条約登録湿地、三河湾国定公園"
  },
  "三重県": {
    "features": "伊勢志摩のリアス式海岸、熊野灘の黒潮域、鈴鹿山脈の落葉樹林。神宮林は数百年の歴史を持つ保護林",
    "endemic_or_notable": "伊勢神宮の神宮林（スギ・ヒノキ巨木林）、熊野のオオダイガハラサンショウウオ、英虞湾の真珠養殖と海草場",
    "biodiversity_note": "神宮林は式年遷宮のために管理されてきた結果、日本最大級の照葉樹林が維持されている",
    "threats": "英虞湾の赤潮、熊野灘の海水温上昇によるサンゴの白化",
    "conservation": "伊勢志摩国立公園、吉野熊野国立公園（三重側）"
  },
  "滋賀県": {
    "features": "琵琶湖を中心とした水環境。日本最大・最古の湖で固有種が多い。周囲の山地と湖が一体の生態系",
    "endemic_or_notable": "琵琶湖固有種（ビワマス、ビワコオオナマズ、セタシジミ等60種以上）",
    "biodiversity_note": "琵琶湖は400万年の歴史を持つ古代湖で世界的に見ても固有種が豊富。水鳥の重要な越冬地",
    "threats": "外来種（ブラックバス・ブルーギル）による在来魚への影響、水草の異常繁茂",
    "conservation": "琵琶湖ラムサール条約登録湿地、琵琶湖国定公園、マザーレイク21計画"
  },
  "京都府": {
    "features": "北山・東山の社寺林、丹後半島の日本海側植生、由良川流域の里山。古都の庭園は数百年の植生管理の結果",
    "endemic_or_notable": "芦生原生林のブナ・トチノキ巨木、鴨川のオオサンショウウオ、丹後のオオミズナギドリ繁殖地",
    "biodiversity_note": "鴨川では市街地でオオサンショウウオが確認される。社寺林は都市の生物多様性の核として機能",
    "threats": "芦生原生林のシカ食害、外来種オオサンショウウオとの交雑、竹林の拡大",
    "conservation": "芦生研究林、山陰海岸国立公園（京都側）、京都の文化的景観と一体の自然保全"
  },
  "大阪府": {
    "features": "大都市圏の中に残る生駒山地・金剛山地の緑地帯、大阪湾岸の人工干潟。淀川・大和川の河川環境",
    "endemic_or_notable": "大阪南港野鳥園のシギ・チドリ、金剛山のブナ林（近畿最低標高のブナ）",
    "biodiversity_note": "大阪城公園は渡り鳥の中継地として都市バードウォッチングの名所。淀川河川敷にはイタセンパラ（天然記念物）が生息",
    "threats": "都市化による緑地の分断、淀川のイタセンパラの個体数減少、外来種",
    "conservation": "金剛生駒紀泉国定公園、淀川のイタセンパラ保全、大阪湾の自然再生事業"
  },
  "兵庫県": {
    "features": "瀬戸内海から日本海まで南北に貫く。六甲山系、但馬のコウノトリ、淡路島の暖地性植物",
    "endemic_or_notable": "豊岡のコウノトリ野生復帰、六甲山のブナ林、淡路島のナルトサワギク問題",
    "biodiversity_note": "コウノトリの野生復帰は日本の種の再導入事業の成功例。但馬の水田環境がコウノトリの餌場として機能",
    "threats": "瀬戸内海の貧栄養化（きれいすぎる海）、六甲山のナラ枯れ",
    "conservation": "コウノトリの郷公園、瀬戸内海国立公園、山陰海岸国立公園（兵庫側）"
  },
  "奈良県": {
    "features": "大台ヶ原・大峯山の原生林、奈良盆地の古墳群周辺の緑地、春日山原始林は社寺林として千年以上保全",
    "endemic_or_notable": "春日山原始林（世界遺産の一部）、大台ヶ原のトウヒ林、奈良公園のニホンジカ",
    "biodiversity_note": "春日山原始林は841年に狩猟伐採が禁じられて以来の照葉樹林。奈良公園のシカは1200頭以上が生息",
    "threats": "大台ヶ原のシカ食害によるトウヒ枯死と笹原化、ナラ枯れ",
    "conservation": "吉野熊野国立公園、春日山原始林（特別天然記念物・世界遺産）"
  },
  "和歌山県": {
    "features": "紀伊半島南端の温暖な気候。黒潮が直接当たる沿岸にサンゴ群落。熊野の深い森林",
    "endemic_or_notable": "串本のテーブルサンゴ群落（本州最大）、熊野のオオダイガハラサンショウウオ、那智の滝周辺の暖温帯林",
    "biodiversity_note": "串本は黒潮の影響で亜熱帯性のサンゴが育つ温帯域の北限。古座川にはオオサンショウウオが生息",
    "threats": "海水温上昇によるサンゴの白化、紀伊半島の豪雨による土砂災害と森林の撹乱",
    "conservation": "吉野熊野国立公園、串本海域公園、熊野古道沿いの森林保全"
  },
  "鳥取県": {
    "features": "鳥取砂丘の風成地形、大山のブナ林、日本海沿岸の松林。中海・宍道湖の汽水環境",
    "endemic_or_notable": "大山のダイセンキャラボク（特別天然記念物）、中海のコハクチョウ、鳥取砂丘の海浜植物",
    "biodiversity_note": "大山は中国地方最高峰で独立峰のため垂直分布帯が明瞭。砂丘は風と砂の動態が独特の生態系を形成",
    "threats": "砂丘の安定化（植生侵入）による砂丘特有の生態系の消失、松枯れ",
    "conservation": "大山隠岐国立公園、中海ラムサール条約登録湿地、鳥取砂丘の除草活動"
  },
  "島根県": {
    "features": "宍道湖・中海の汽水域、隠岐諸島の独自の生物相、石見銀山周辺の二次林",
    "endemic_or_notable": "宍道湖のヤマトシジミ、隠岐のオキサンショウウオ、隠岐のダイセンキャラボク天然林",
    "biodiversity_note": "隠岐諸島は氷期に大陸と陸続きだった名残で大陸系の植物が残る。宍道湖は汽水湖として独特の生態系",
    "threats": "宍道湖の水環境変化によるシジミ資源の減少、隠岐の過疎化に伴う里山管理の低下",
    "conservation": "大山隠岐国立公園、宍道湖ラムサール条約登録湿地、隠岐ユネスコジオパーク"
  },
  "岡山県": {
    "features": "瀬戸内海の温暖少雨な気候。児島湾干拓地の農地、吉備高原の里山、蒜山高原の草原",
    "endemic_or_notable": "蒜山のジャージー牧場周辺の草原生態系、岡山後楽園のタンチョウ飼育、児島湖の水鳥",
    "biodiversity_note": "瀬戸内海の島々は隔離された環境で独自の個体群を維持。吉備路の里山は古くからの土地利用が継続",
    "threats": "瀬戸内海の貧栄養化、里山の管理放棄による竹林化、外来種",
    "conservation": "瀬戸内海国立公園、蒜山高原の草原管理、大山隠岐国立公園（岡山側）"
  },
  "広島県": {
    "features": "瀬戸内海の多島美、宮島の原生林、太田川デルタの河川環境。県北部は中国山地のブナ林",
    "endemic_or_notable": "宮島の暖温帯原生林（天然記念物）、太田川のアユ、芸北の湿原",
    "biodiversity_note": "宮島は厳島神社とともに島全体が信仰の対象で原生林が守られてきた。太田川は都市河川ながらオオサンショウウオが生息",
    "threats": "瀬戸内海の海砂採取の影響、ナラ枯れ、シカの増加",
    "conservation": "瀬戸内海国立公園、宮島の天然記念物指定林、芸北の湿原保全"
  },
  "山口県": {
    "features": "本州最西端。瀬戸内海と日本海の両方に面し、関門海峡で九州と至近。秋吉台のカルスト地形",
    "endemic_or_notable": "秋吉台の石灰岩草原と鍾乳洞生物、周防大島のニホンアワサンゴ群集、見島のカラスバト",
    "biodiversity_note": "秋吉台は日本最大のカルスト台地で石灰岩に適応した固有の洞窟性生物が生息。関門海峡は生物地理の境界線の一つ",
    "threats": "秋吉台の草原維持（山焼きの担い手不足）、瀬戸内海の環境変化",
    "conservation": "秋吉台国定公園、瀬戸内海国立公園、北長門海岸国定公園"
  },
  "徳島県": {
    "features": "吉野川の急流と四国山地の深い森。剣山系には冷温帯の植生が残る。鳴門海峡の渦潮",
    "endemic_or_notable": "剣山のキレンゲショウマ群落、吉野川のアユ、出羽島の海鳥",
    "biodiversity_note": "四国山地の渓谷にはカワガラスやヤマセミが生息。鳴門海峡の潮流は独特の海洋生態系を形成",
    "threats": "吉野川の河口干潟開発問題（住民投票で回避）、スギ・ヒノキ人工林の管理不足",
    "conservation": "剣山国定公園、吉野川河口の保全、鳴門海峡の自然環境"
  },
  "香川県": {
    "features": "日本最小の県だが瀬戸内海の島々を含む。讃岐平野のため池群は独特の水辺環境を形成",
    "endemic_or_notable": "讃岐平野の14000以上のため池生態系、小豆島の寒霞渓（渓谷の紅葉）",
    "biodiversity_note": "ため池密度が日本一高く、それぞれが小さな湿地生態系として機能。トンボや水生植物の多様性が高い",
    "threats": "ため池の管理放棄・埋立て、瀬戸内海の環境変化",
    "conservation": "瀬戸内海国立公園、ため池の生態系保全、小豆島の寒霞渓"
  },
  "愛媛県": {
    "features": "石鎚山（西日本最高峰）の高山植物帯、しまなみ海道沿いの瀬戸内海島嶼部、宇和海の亜熱帯性海洋生物",
    "endemic_or_notable": "石鎚山のイシヅチザクラ、宇和海のサンゴ、佐田岬のサシバ渡り観察地",
    "biodiversity_note": "佐田岬半島は秋にサシバやハチクマの渡りルート上にあたり、タカの渡りの観察名所",
    "threats": "宇和海の海水温上昇によるサンゴの白化、みかん畑の耕作放棄",
    "conservation": "石鎚国定公園、足摺宇和海国立公園（愛媛側）、瀬戸内海国立公園"
  },
  "高知県": {
    "features": "四万十川の清流、足摺岬の亜熱帯性植生、四国カルスト。黒潮が直接当たる太平洋岸",
    "endemic_or_notable": "四万十川のアカメ、ニホンカワウソ（最後の確認地）、横倉山の植物群落",
    "biodiversity_note": "四万十川は「日本最後の清流」と呼ばれアユ・テナガエビなど豊かな淡水生態系。足摺岬周辺は亜熱帯性植物の北限",
    "threats": "四万十川流域の過疎化と水利用の変化、太平洋岸の高波による海岸浸食",
    "conservation": "足摺宇和海国立公園、四万十川の自然環境保全、横倉山県立自然公園"
  },
  "福岡県": {
    "features": "玄界灘と瀬戸内海に面し、筑紫平野の水田地帯、英彦山の山地林。対馬海流の影響で温暖",
    "endemic_or_notable": "和白干潟のクロツラヘラサギ、英彦山のブナ林、曽根干潟のカブトガニ",
    "biodiversity_note": "和白干潟は博多湾に残る貴重な干潟で絶滅危惧種クロツラヘラサギが越冬。曽根干潟は「生きた化石」カブトガニの繁殖地",
    "threats": "博多湾の開発圧、干潟の埋立、外来種ナルトサワギクの拡散",
    "conservation": "和白干潟の保全活動、曽根干潟のカブトガニ保護、英彦山の天然林保護"
  },
  "佐賀県": {
    "features": "有明海の広大な干潟は日本最大の干潟面積。背後に脊振山地の森林が広がる",
    "endemic_or_notable": "有明海のムツゴロウ・ワラスボ・シオマネキ、東よか干潟のシギ・チドリ",
    "biodiversity_note": "有明海の干潟は潮の干満差が最大6mに達し、広大な泥干潟が出現。ムツゴロウなど有明海固有の生物が生息",
    "threats": "諫早湾干拓による有明海の環境変化、ノリ養殖への影響",
    "conservation": "東よか干潟ラムサール条約登録湿地、有明海の環境保全"
  },
  "長崎県": {
    "features": "日本一多い971の島々を持つ。対馬は大陸との生物地理的つながりが強い。西海の沈降海岸",
    "endemic_or_notable": "対馬のツシマヤマネコ（絶滅危惧IA類）、五島列島の海鳥繁殖地、雲仙のミヤマキリシマ",
    "biodiversity_note": "対馬は大陸系の動植物が残る生物地理学的に重要な島。ツシマヤマネコは推定100頭前後",
    "threats": "ツシマヤマネコの交通事故死、離島の過疎化による里山管理の崩壊",
    "conservation": "対馬のツシマヤマネコ保護事業、西海国立公園、雲仙天草国立公園"
  },
  "熊本県": {
    "features": "阿蘇カルデラの広大な草原、球磨川の急流、天草の海岸。阿蘇の草原は千年以上の野焼きで維持",
    "endemic_or_notable": "阿蘇の草原性植物・昆虫、球磨川のアユ・ヤマメ、天草のイルカウォッチング",
    "biodiversity_note": "阿蘇の草原は人為的な野焼きで維持された半自然草原で、ヒゴタイやハナシノブなど希少な草原性植物が生育",
    "threats": "阿蘇の野焼き参加者の減少、球磨川流域の豪雨災害、熊本地震後の地形変化",
    "conservation": "阿蘇くじゅう国立公園、阿蘇の草原維持活動（野焼き）、天草のイルカ保全"
  },
  "大分県": {
    "features": "くじゅう連山の高原、別府の温泉地形、国東半島の六郷満山文化の森。豊後水道の豊かな漁場",
    "endemic_or_notable": "くじゅうのミヤマキリシマ大群落、別府の温泉微生物、国東半島のオオイタサンショウウオ",
    "biodiversity_note": "くじゅう連山は九州の高山植物の中心地。坊ガツル湿原はラムサール条約登録湿地で希少な湿原植物が生育",
    "threats": "くじゅうの登山道沿いの踏圧、ミヤマキリシマへの病害虫",
    "conservation": "阿蘇くじゅう国立公園、坊ガツル湿原ラムサール条約登録湿地"
  },
  "宮崎県": {
    "features": "日南海岸の亜熱帯性植生、高千穂峡の柱状節理、霧島連山の火山帯。照葉樹林の保存状態が良い",
    "endemic_or_notable": "綾の照葉樹林（日本最大級）、青島の亜熱帯植物群落、霧島のノカイドウ（霧島固有種）",
    "biodiversity_note": "綾の照葉樹林はユネスコエコパークに登録された九州最大の原生的な照葉樹林",
    "threats": "照葉樹林周辺のスギ人工林の管理不足、シカの増加、台風による撹乱",
    "conservation": "綾ユネスコエコパーク、霧島錦江湾国立公園、日南海岸国定公園"
  },
  "鹿児島県": {
    "features": "桜島の活火山、屋久島の世界遺産の森、奄美大島の亜熱帯照葉樹林。南北600kmに及ぶ広大な県域",
    "endemic_or_notable": "屋久杉の巨木林、奄美のアマミノクロウサギ、桜島の火山適応生物",
    "biodiversity_note": "屋久島は洋上アルプスと呼ばれ亜熱帯から亜高山帯まで垂直分布が凝縮。奄美は世界自然遺産に登録",
    "threats": "奄美のマングース（駆除が進み成果）、屋久島のヤクシカ増加、サンゴ礁の白化",
    "conservation": "屋久島・奄美大島世界自然遺産、霧島錦江湾国立公園、奄美群島国立公園"
  },
  "沖縄県": {
    "features": "亜熱帯気候の島嶼群。サンゴ礁に囲まれた島々と北部やんばるの照葉樹林。独自の進化を遂げた生物相",
    "endemic_or_notable": "ヤンバルクイナ、イリオモテヤマネコ、ノグチゲラ、慶良間のサンゴ礁、西表のマングローブ",
    "biodiversity_note": "琉球列島は大陸から分離した島嶼で固有種率が高い。やんばるの森は世界自然遺産に登録されたホットスポット",
    "threats": "サンゴの白化・オニヒトデ被害、基地建設による自然破壊（辺野古）、外来種（マングース・グリーンアノール）",
    "conservation": "やんばる・西表島世界自然遺産、慶良間諸島国立公園、西表石垣国立公園"
  }
}
