{
    "id": "paper_3dbc07d80ff4d909e180e6b0adffc29d",
    "doi": "10.15845\/on.v31i0.166",
    "title": "Wintering Red-breasted Merganser Mergus serrator preying on pipefish in coastal Western Norway",
    "year": 2008,
    "container_title": "Ornis Norvegica",
    "type": "journal-article",
    "url": "https:\/\/doi.org\/10.15845\/on.v31i0.166",
    "source": "crossref",
    "registry_run": "20260207_104759",
    "tier": 1,
    "dublin_core": {
        "dc:identifier": "doi:10.15845\/on.v31i0.166",
        "dc:title": "Wintering Red-breasted Merganser Mergus serrator preying on pipefish in coastal Western Norway",
        "dc:date": 2008,
        "dc:source": "Ornis Norvegica",
        "dc:type": "journal-article",
        "dc:format": "application\/json"
    }
}