{
    "id": "paper_13e504e5e54e5ccc33c513fe0a3d3de7",
    "doi": "10.3838\/jjo.73.107",
    "title": "Courtship and mating behavior of Japanese Night Heron &lt;i&gt;Gorsachius goisagi&lt;\/i&gt; observed during the breeding season",
    "year": 2024,
    "container_title": "Japanese Journal of Ornithology",
    "type": "journal-article",
    "url": "https:\/\/doi.org\/10.3838\/jjo.73.107",
    "source": "crossref",
    "registry_run": "20260207_104759",
    "tier": 1,
    "dublin_core": {
        "dc:identifier": "doi:10.3838\/jjo.73.107",
        "dc:title": "Courtship and mating behavior of Japanese Night Heron &lt;i&gt;Gorsachius goisagi&lt;\/i&gt; observed during the breeding season",
        "dc:date": 2024,
        "dc:source": "Japanese Journal of Ornithology",
        "dc:type": "journal-article",
        "dc:format": "application\/json"
    }
}