{
    "id": "paper_554f1d9190f8bfd474019e4c0afc72c7",
    "doi": "10.11646\/zootaxa.1664.1.2",
    "title": "Two new species of Coenagrion Kirby, 1890, from China (Odonata: Zygoptera: Coenagrionidae)",
    "year": 2007,
    "container_title": "Zootaxa",
    "type": "journal-article",
    "url": "https:\/\/doi.org\/10.11646\/zootaxa.1664.1.2",
    "source": "crossref",
    "registry_run": "20260207_104759",
    "tier": 1,
    "dublin_core": {
        "dc:identifier": "doi:10.11646\/zootaxa.1664.1.2",
        "dc:title": "Two new species of Coenagrion Kirby, 1890, from China (Odonata: Zygoptera: Coenagrionidae)",
        "dc:date": 2007,
        "dc:source": "Zootaxa",
        "dc:type": "journal-article",
        "dc:format": "application\/json"
    }
}