{
    "id": "paper_6dfb3182d776fe459a1ba506a14dff26",
    "doi": "10.21203\/rs.3.rs-3971219\/v1",
    "title": "More than stridulation: signal interaction and constraint in the complex vibroacoustic courtship of a cricket",
    "year": 2024,
    "container_title": "",
    "type": "posted-content",
    "url": "https:\/\/doi.org\/10.21203\/rs.3.rs-3971219\/v1",
    "source": "crossref",
    "registry_run": "20260207_104759",
    "tier": 1,
    "dublin_core": {
        "dc:identifier": "doi:10.21203\/rs.3.rs-3971219\/v1",
        "dc:title": "More than stridulation: signal interaction and constraint in the complex vibroacoustic courtship of a cricket",
        "dc:date": 2024,
        "dc:source": "",
        "dc:type": "posted-content",
        "dc:format": "application\/json"
    }
}