{
    "id": "paper_2e38c38f47c139002aa8874d375b2284",
    "doi": "10.1006\/anbe.1996.0018",
    "title": "Territoriality and the function of song in the primitive acoustic insect (Orthoptera: Haglidae)",
    "year": 1996,
    "container_title": "Animal Behaviour",
    "type": "journal-article",
    "url": "https:\/\/doi.org\/10.1006\/anbe.1996.0018",
    "source": "crossref",
    "registry_run": "20260207_104759",
    "tier": 1,
    "dublin_core": {
        "dc:identifier": "doi:10.1006\/anbe.1996.0018",
        "dc:title": "Territoriality and the function of song in the primitive acoustic insect (Orthoptera: Haglidae)",
        "dc:date": 1996,
        "dc:source": "Animal Behaviour",
        "dc:type": "journal-article",
        "dc:format": "application\/json"
    }
}