{
    "id": "paper_594d93b1901eafaf11f705f9b87cfd15",
    "doi": "10.1111\/icad.12229",
    "title": "Insights into the ecology, genetics and distribution of\n                    Lucanus elaphus\n                    Fabricius (Coleoptera: Lucanidae), North America's giant stag beetle",
    "year": 2017,
    "container_title": "Insect Conservation and Diversity",
    "type": "journal-article",
    "url": "https:\/\/doi.org\/10.1111\/icad.12229",
    "source": "crossref",
    "registry_run": "20260207_104759",
    "tier": 1
}