{
    "id": "ptl_paper_86e9c68b747c5f61c7320f9cdfca068e_8ff88b7c9b3b4dac528929cb27cd21ac",
    "paper_id": "paper_86e9c68b747c5f61c7320f9cdfca068e",
    "doi": "10.21203\/rs.3.rs-2224956\/v1",
    "query_id": "jp_bird_2480353_en",
    "query_label": "Pelecanus crispus Japan (ecology\/distribution)",
    "scientific_name": "Pelecanus crispus",
    "jp_name": null,
    "darwin_core": {
        "dwc:associatedReferences": "doi:10.21203\/rs.3.rs-2224956\/v1",
        "dwc:scientificName": "Pelecanus crispus",
        "dwc:vernacularName": null,
        "dwc:taxonConceptID": "gbif:2480353",
        "dwc:taxonomicStatus": "ACCEPTED",
        "dwc:originalNameUsage": "Pelecanus crispus",
        "dwc:nameAccordingTo": "Crossref_Query",
        "dwc:family": "Pelecanidae"
    },
    "gbif_taxon_key": 2480353,
    "gbif_status": "ACCEPTED",
    "gbif_accepted_name": null,
    "gbif_accepted_key": null,
    "gbif_family": "Pelecanidae"
}