{
    "id": "ptl_paper_620c3747459ac7c470d656ac3d9b2287_53c0407e42654e02637cb46efb9a2dd0",
    "paper_id": "paper_620c3747459ac7c470d656ac3d9b2287",
    "doi": "10.32003\/igge.854992",
    "query_id": "psittacula_krameri_jp",
    "query_label": "Psittacula krameri (Ring-necked parakeet) Japan",
    "scientific_name": "Psittacula krameri",
    "jp_name": null,
    "gbif_taxon_key": 2479226,
    "gbif_status": "ACCEPTED",
    "gbif_accepted_name": null,
    "gbif_accepted_key": null,
    "gbif_family": "Psittacidae"
}