{
    "id": "ptl_paper_767d4b1d5542c26a32cd2e9f8aa698b8_680d340de23a94c1fa34be7f0d8f6f60",
    "paper_id": "paper_767d4b1d5542c26a32cd2e9f8aa698b8",
    "doi": "10.1016\/j.anbehav.2005.09.014",
    "query_id": "jp_bird_5232446_en",
    "query_label": "Branta bernicla Japan (ecology\/distribution)",
    "scientific_name": "Branta bernicla",
    "jp_name": null,
    "gbif_taxon_key": 5232446,
    "gbif_status": "ACCEPTED",
    "gbif_accepted_name": null,
    "gbif_accepted_key": null,
    "gbif_family": "Anatidae"
}