{
    "id": "ptl_paper_7ecc9cfd7bde14887f4b7b56f5c81675_dc4db780b043e59521fe244beddab621",
    "paper_id": "paper_7ecc9cfd7bde14887f4b7b56f5c81675",
    "doi": "10.1007\/s11284-007-0402-z",
    "query_id": "jp_insect_sasakia_charonda",
    "query_label": "Sasakia charonda Japan (Ohmurasaki)",
    "scientific_name": "Sasakia charonda",
    "jp_name": null,
    "gbif_taxon_key": 5128519,
    "gbif_status": "ACCEPTED",
    "gbif_accepted_name": null,
    "gbif_accepted_key": null,
    "gbif_family": "Nymphalidae"
}