{
    "id": "ptl_paper_4df0bcdb074b2f6c08f4fa29f3a9b6c7_7eefeeca6f70bab7f4b659b844111be4",
    "paper_id": "paper_4df0bcdb074b2f6c08f4fa29f3a9b6c7",
    "doi": "10.5852\/ejt.2024.943.2601",
    "query_id": "jp_birds_checklist_general",
    "query_label": "Japan bird checklist taxonomy",
    "scientific_name": "Japan bird",
    "jp_name": null,
    "darwin_core": {
        "dwc:associatedReferences": "doi:10.5852\/ejt.2024.943.2601",
        "dwc:scientificName": "Japan bird",
        "dwc:vernacularName": null
    }
}