[
    {
        "id": "obs_69548f9a56067",
        "user_id": "user_69548f9a55ed9",
        "user_name": "佐々木 誠",
        "user_avatar": "https:\/\/i.pravatar.cc\/150?u=user_69548f9a55ed9",
        "user_rank": "観察者",
        "photos": [
            "uploads\/sample_insect.png"
        ],
        "observed_at": "2025-08-31 17:38:10",
        "created_at": "2025-08-31 17:38:10",
        "lat": 34.737069999999996,
        "lng": 137.71561,
        "cultivation": "wild",
        "note": "動きが早かった。 #139",
        "status": "Research Grade",
        "taxon": {
            "key": "22247a3c217fe22c007b22e12483b065",
            "name": "モンシロチョウ",
            "scientific_name": "Pieris rapae",
            "rank": "species"
        }
    },
    {
        "id": "obs_69548f9a55fd2",
        "user_id": "user_69548f9a55eee",
        "user_name": "中村 陽菜",
        "user_avatar": "https:\/\/i.pravatar.cc\/150?u=user_69548f9a55eee",
        "user_rank": "ビギナー",
        "photos": [
            "uploads\/sample_mammal.png"
        ],
        "observed_at": "2025-08-31 10:16:27",
        "created_at": "2025-08-31 10:16:27",
        "lat": 34.70405,
        "lng": 137.76706000000001,
        "cultivation": "cultivated",
        "note": "大量に発生していました。 #59",
        "status": "Research Grade",
        "taxon": {
            "key": "0107d09aca873dfef5fbf7f5daa28f40",
            "name": "アライグマ",
            "scientific_name": "Procyon lotor",
            "rank": "species"
        }
    },
    {
        "id": "obs_69548f9a56040",
        "user_id": "user_69548f9a55eda",
        "user_name": "斎藤 葵",
        "user_avatar": "https:\/\/i.pravatar.cc\/150?u=user_69548f9a55eda",
        "user_rank": "観察者",
        "photos": [
            "uploads\/sample_fish.png"
        ],
        "observed_at": "2025-08-30 17:11:31",
        "created_at": "2025-08-30 17:11:31",
        "lat": 34.740719999999996,
        "lng": 137.80204,
        "cultivation": "wild",
        "note": "これは何でしょうか？ #117",
        "status": "Needs ID",
        "taxon": {
            "key": "812b1f2690fb5f898ff7521d9475a5ea",
            "name": "コイ",
            "scientific_name": "Cyprinus carpio",
            "rank": "species"
        }
    },
    {
        "id": "obs_69548f9a55ff2",
        "user_id": "user_69548f9a55ee1",
        "user_name": "中島 大樹",
        "user_avatar": "https:\/\/i.pravatar.cc\/150?u=user_69548f9a55ee1",
        "user_rank": "観察者",
        "photos": [
            "uploads\/sample_insect.png"
        ],
        "observed_at": "2025-08-30 04:23:25",
        "created_at": "2025-08-30 04:23:25",
        "lat": 34.6333,
        "lng": 137.78445,
        "cultivation": "wild",
        "note": "綺麗な色でした。 #73",
        "status": "Needs ID",
        "taxon": {
            "key": "7239cc8b5b5fdbd1ee351ae6ad7807cd",
            "name": "ショウリョウバッタ",
            "scientific_name": "Acrida cinerea",
            "rank": "species"
        }
    },
    {
        "id": "obs_69548f9a5604d",
        "user_id": "user_ya_001",
        "user_name": "八巻 毅",
        "user_avatar": "https:\/\/i.pravatar.cc\/300?u=yamaki",
        "user_rank": "認定研究者",
        "photos": [
            "uploads\/sample_mammal.png"
        ],
        "observed_at": "2025-08-29 09:04:19",
        "created_at": "2025-08-29 09:04:19",
        "lat": 34.64647,
        "lng": 137.7173,
        "cultivation": "wild",
        "note": "これは何でしょうか？ #125",
        "status": "Research Grade",
        "taxon": {
            "key": "91fdc6d57960ec1a1a0e0d9df1e2ab00",
            "name": "ハクビシン",
            "scientific_name": "Paguma larvata",
            "rank": "species"
        }
    },
    {
        "id": "obs_69548f9a55f33",
        "user_id": "user_69548f9a55eb8",
        "user_name": "阿部 誠",
        "user_avatar": "https:\/\/i.pravatar.cc\/150?u=user_69548f9a55eb8",
        "user_rank": "熟練者",
        "photos": [
            "uploads\/sample_mammal.png"
        ],
        "observed_at": "2025-08-28 11:19:24",
        "created_at": "2025-08-28 11:19:24",
        "lat": 34.64214,
        "lng": 137.66222,
        "cultivation": "wild",
        "note": " #3",
        "status": "Needs ID",
        "taxon": {
            "key": "b021e922012611f4807f2222eeef54df",
            "name": "タヌキ",
            "scientific_name": "Nyctereutes procyonoides",
            "rank": "species"
        }
    },
    {
        "id": "obs_69548f9a560d7",
        "user_id": "user_69548f9a55ee6",
        "user_name": "石井 誠",
        "user_avatar": "https:\/\/i.pravatar.cc\/150?u=user_69548f9a55ee6",
        "user_rank": "観察者",
        "photos": [
            "uploads\/sample_insect.png"
        ],
        "observed_at": "2025-08-27 14:38:15",
        "created_at": "2025-08-27 14:38:15",
        "lat": 34.63283,
        "lng": 137.77648,
        "cultivation": "wild",
        "note": "公園で見つけました。 #196",
        "status": "Casual",
        "taxon": {
            "key": "5e8ba5334afd1f8c569b10cb8e694bd2",
            "name": "オニヤンマ",
            "scientific_name": "Anotogaster sieboldii",
            "rank": "species"
        }
    },
    {
        "id": "obs_69548f9a5607e",
        "user_id": "user_69548f9a55ef8",
        "user_name": "渡辺 愛",
        "user_avatar": "https:\/\/i.pravatar.cc\/150?u=user_69548f9a55ef8",
        "user_rank": "ビギナー",
        "photos": [
            "uploads\/sample_fish.png"
        ],
        "observed_at": "2025-08-27 07:27:08",
        "created_at": "2025-08-27 07:27:08",
        "lat": 34.66695,
        "lng": 137.64794,
        "cultivation": "cultivated",
        "note": "公園で見つけました。 #152",
        "status": "Research Grade",
        "taxon": {
            "key": "907e98b5fdcf7000fac6362b543efac6",
            "name": "メダカ",
            "scientific_name": "Oryzias latipes",
            "rank": "species"
        }
    },
    {
        "id": "obs_69548f9a55f53",
        "user_id": "user_69548f9a55f07",
        "user_name": "清水 翔太",
        "user_avatar": "https:\/\/i.pravatar.cc\/150?u=user_69548f9a55f07",
        "user_rank": "ビギナー",
        "photos": [
            "uploads\/sample_flower.png"
        ],
        "observed_at": "2025-08-26 18:33:38",
        "created_at": "2025-08-26 18:33:38",
        "lat": 34.70442,
        "lng": 137.75761,
        "cultivation": "wild",
        "note": "動きが早かった。 #14",
        "status": "Research Grade",
        "taxon": {
            "key": "830eeb2309a16036bb6f66b7e1254835",
            "name": "アジサイ",
            "scientific_name": "Hydrangea macrophylla",
            "rank": "species"
        }
    },
    {
        "id": "obs_69548f9a560b9",
        "user_id": "user_69548f9a55eed",
        "user_name": "小川 健一",
        "user_avatar": "https:\/\/i.pravatar.cc\/150?u=user_69548f9a55eed",
        "user_rank": "観察者",
        "photos": [
            "uploads\/sample_fish.png"
        ],
        "observed_at": "2025-08-26 11:22:04",
        "created_at": "2025-08-26 11:22:04",
        "lat": 34.78853,
        "lng": 137.65712,
        "cultivation": "wild",
        "note": " #178",
        "status": "Needs ID",
        "taxon": {
            "key": "812b1f2690fb5f898ff7521d9475a5ea",
            "name": "コイ",
            "scientific_name": "Cyprinus carpio",
            "rank": "species"
        }
    },
    {
        "id": "obs_69548f9a560cd",
        "user_id": "user_69548f9a55eec",
        "user_name": "山口 三郎",
        "user_avatar": "https:\/\/i.pravatar.cc\/150?u=user_69548f9a55eec",
        "user_rank": "ビギナー",
        "photos": [
            "uploads\/sample_insect.png"
        ],
        "observed_at": "2025-08-23 19:44:17",
        "created_at": "2025-08-23 19:44:17",
        "lat": 34.64163,
        "lng": 137.77605,
        "cultivation": "wild",
        "note": " #190",
        "status": "Research Grade",
        "taxon": {
            "key": "6681e1d7eb8e414ef709c80587416a28",
            "name": "カブトムシ",
            "scientific_name": "Trypoxylus dichotomus",
            "rank": "species"
        }
    },
    {
        "id": "obs_69548f9a55ffc",
        "user_id": "user_69548f9a55ee4",
        "user_name": "中村 翼",
        "user_avatar": "https:\/\/i.pravatar.cc\/150?u=user_69548f9a55ee4",
        "user_rank": "ビギナー",
        "photos": [
            "uploads\/sample_insect.png"
        ],
        "observed_at": "2025-08-23 13:42:05",
        "created_at": "2025-08-23 13:42:05",
        "lat": 34.77664,
        "lng": 137.72849,
        "cultivation": "wild",
        "note": "動きが早かった。 #79",
        "status": "Needs ID",
        "taxon": {
            "key": "890e2525facb93c584dd1e223c8836c4",
            "name": "ナナホシテントウ",
            "scientific_name": "Coccinella septempunctata",
            "rank": "species"
        }
    },
    {
        "id": "obs_69548f9a55fc3",
        "user_id": "user_69548f9a55f07",
        "user_name": "清水 翔太",
        "user_avatar": "https:\/\/i.pravatar.cc\/150?u=user_69548f9a55f07",
        "user_rank": "ビギナー",
        "photos": [
            "uploads\/sample_fish.png"
        ],
        "observed_at": "2025-08-23 00:43:15",
        "created_at": "2025-08-23 00:43:15",
        "lat": 34.68824,
        "lng": 137.68705,
        "cultivation": "wild",
        "note": "初めて見ました！ #53",
        "status": "Research Grade",
        "taxon": {
            "key": "9332a61fa68760db1984f08b2ffbe46f",
            "name": "オイカワ",
            "scientific_name": "Opsariichthys platypus",
            "rank": "species"
        }
    },
    {
        "id": "obs_69548f9a560c1",
        "user_id": "user_69548f9a55ee3",
        "user_name": "林 陽菜",
        "user_avatar": "https:\/\/i.pravatar.cc\/150?u=user_69548f9a55ee3",
        "user_rank": "観察者",
        "photos": [
            "uploads\/sample_flower.png"
        ],
        "observed_at": "2025-08-22 23:31:12",
        "created_at": "2025-08-22 23:31:12",
        "lat": 34.72087,
        "lng": 137.68628,
        "cultivation": "wild",
        "note": " #183",
        "status": "Research Grade",
        "taxon": {
            "key": "aa3561d12b4a04f0a164ea0bd5d3ab90",
            "name": "ヒマワリ",
            "scientific_name": "Helianthus annuus",
            "rank": "species"
        }
    },
    {
        "id": "obs_69548f9a56007",
        "user_id": "user_69548f9a55ede",
        "user_name": "佐々木 智子",
        "user_avatar": "https:\/\/i.pravatar.cc\/150?u=user_69548f9a55ede",
        "user_rank": "観察者",
        "photos": [
            "uploads\/sample_flower.png"
        ],
        "observed_at": "2025-08-22 06:07:58",
        "created_at": "2025-08-22 06:07:58",
        "lat": 34.783809999999995,
        "lng": 137.65519,
        "cultivation": "wild",
        "note": "家の近くです。 #86",
        "status": "Casual",
        "taxon": {
            "key": "aa3561d12b4a04f0a164ea0bd5d3ab90",
            "name": "ヒマワリ",
            "scientific_name": "Helianthus annuus",
            "rank": "species"
        }
    },
    {
        "id": "obs_69548f9a55fd4",
        "user_id": "user_69548f9a55ee1",
        "user_name": "中島 大樹",
        "user_avatar": "https:\/\/i.pravatar.cc\/150?u=user_69548f9a55ee1",
        "user_rank": "観察者",
        "photos": [
            "uploads\/sample_flower.png"
        ],
        "observed_at": "2025-08-22 03:24:57",
        "created_at": "2025-08-22 03:24:57",
        "lat": 34.71822,
        "lng": 137.75412,
        "cultivation": "wild",
        "note": " #60",
        "status": "Research Grade",
        "taxon": {
            "key": "830eeb2309a16036bb6f66b7e1254835",
            "name": "アジサイ",
            "scientific_name": "Hydrangea macrophylla",
            "rank": "species"
        }
    },
    {
        "id": "obs_69548f9a5601c",
        "user_id": "user_69548f9a55edc",
        "user_name": "山田 大樹",
        "user_avatar": "https:\/\/i.pravatar.cc\/150?u=user_69548f9a55edc",
        "user_rank": "認定研究者",
        "photos": [
            "uploads\/sample_plant.png"
        ],
        "observed_at": "2025-08-20 19:50:20",
        "created_at": "2025-08-20 19:50:20",
        "lat": 34.63443,
        "lng": 137.69287,
        "cultivation": "wild",
        "note": " #98",
        "status": "Research Grade",
        "taxon": {
            "key": "68f08be4b2a13127a7454b96a240f4d6",
            "name": "セイヨウタンポポ",
            "scientific_name": "Taraxacum officinale",
            "rank": "species"
        }
    },
    {
        "id": "obs_69548f9a5601a",
        "user_id": "user_69548f9a55edb",
        "user_name": "田中 真由美",
        "user_avatar": "https:\/\/i.pravatar.cc\/150?u=user_69548f9a55edb",
        "user_rank": "認定研究者",
        "photos": [
            "uploads\/sample_flower.png"
        ],
        "observed_at": "2025-08-18 08:23:36",
        "created_at": "2025-08-18 08:23:36",
        "lat": 34.63415,
        "lng": 137.69568,
        "cultivation": "wild",
        "note": " #97",
        "status": "Research Grade",
        "taxon": {
            "key": "aa3561d12b4a04f0a164ea0bd5d3ab90",
            "name": "ヒマワリ",
            "scientific_name": "Helianthus annuus",
            "rank": "species"
        }
    },
    {
        "id": "obs_69548f9a5609e",
        "user_id": "user_69548f9a55ee5",
        "user_name": "林 拓海",
        "user_avatar": "https:\/\/i.pravatar.cc\/150?u=user_69548f9a55ee5",
        "user_rank": "博士",
        "photos": [
            "uploads\/sample_fish.png"
        ],
        "observed_at": "2025-08-17 07:54:48",
        "created_at": "2025-08-17 07:54:48",
        "lat": 34.71245,
        "lng": 137.65987,
        "cultivation": "wild",
        "note": " #163",
        "status": "Research Grade",
        "taxon": {
            "key": "812b1f2690fb5f898ff7521d9475a5ea",
            "name": "コイ",
            "scientific_name": "Cyprinus carpio",
            "rank": "species"
        }
    },
    {
        "id": "obs_69548f9a560db",
        "user_id": "user_69548f9a55edf",
        "user_name": "井上 結衣",
        "user_avatar": "https:\/\/i.pravatar.cc\/150?u=user_69548f9a55edf",
        "user_rank": "観察者",
        "photos": [
            "uploads\/sample_mammal.png"
        ],
        "observed_at": "2025-08-16 13:53:03",
        "created_at": "2025-08-16 13:53:03",
        "lat": 34.657469999999996,
        "lng": 137.74543,
        "cultivation": "wild",
        "note": "動きが早かった。 #198",
        "status": "Needs ID",
        "taxon": {
            "key": "b021e922012611f4807f2222eeef54df",
            "name": "タヌキ",
            "scientific_name": "Nyctereutes procyonoides",
            "rank": "species"
        }
    },
    {
        "id": "obs_69548f9a5603e",
        "user_id": "user_69548f9a55efd",
        "user_name": "阿部 智子",
        "user_avatar": "https:\/\/i.pravatar.cc\/150?u=user_69548f9a55efd",
        "user_rank": "熟練者",
        "photos": [
            "uploads\/sample_mammal.png"
        ],
        "observed_at": "2025-08-14 11:46:06",
        "created_at": "2025-08-14 11:46:06",
        "lat": 34.72483,
        "lng": 137.79575,
        "cultivation": "wild",
        "note": "綺麗な色でした。 #116",
        "status": "Needs ID",
        "taxon": {
            "key": "b021e922012611f4807f2222eeef54df",
            "name": "タヌキ",
            "scientific_name": "Nyctereutes procyonoides",
            "rank": "species"
        }
    },
    {
        "id": "obs_69548f9a55f59",
        "user_id": "user_69548f9a55efb",
        "user_name": "中島 花子",
        "user_avatar": "https:\/\/i.pravatar.cc\/150?u=user_69548f9a55efb",
        "user_rank": "観察者",
        "photos": [
            "uploads\/sample_insect.png"
        ],
        "observed_at": "2025-08-14 06:36:21",
        "created_at": "2025-08-14 06:36:21",
        "lat": 34.71212,
        "lng": 137.76291,
        "cultivation": "wild",
        "note": "大量に発生していました。 #17",
        "status": "Needs ID",
        "taxon": {
            "key": "22247a3c217fe22c007b22e12483b065",
            "name": "モンシロチョウ",
            "scientific_name": "Pieris rapae",
            "rank": "species"
        }
    },
    {
        "id": "obs_69548f9a56088",
        "user_id": "user_69548f9a55efd",
        "user_name": "阿部 智子",
        "user_avatar": "https:\/\/i.pravatar.cc\/150?u=user_69548f9a55efd",
        "user_rank": "熟練者",
        "photos": [
            "uploads\/sample_bird.png"
        ],
        "observed_at": "2025-08-13 17:33:26",
        "created_at": "2025-08-13 17:33:26",
        "lat": 34.68712,
        "lng": 137.69963,
        "cultivation": "wild",
        "note": "大量に発生していました。 #157",
        "status": "Research Grade",
        "taxon": {
            "key": "5c6614249f02d9e594d3fd4b98278592",
            "name": "スズメ",
            "scientific_name": "Passer montanus",
            "rank": "species"
        }
    },
    {
        "id": "obs_69548f9a55f92",
        "user_id": "user_69548f9a55eda",
        "user_name": "斎藤 葵",
        "user_avatar": "https:\/\/i.pravatar.cc\/150?u=user_69548f9a55eda",
        "user_rank": "観察者",
        "photos": [
            "uploads\/sample_fish.png"
        ],
        "observed_at": "2025-08-11 07:55:47",
        "created_at": "2025-08-11 07:55:47",
        "lat": 34.68204,
        "lng": 137.73687,
        "cultivation": "wild",
        "note": "これは何でしょうか？ #40",
        "status": "Research Grade",
        "taxon": {
            "key": "9332a61fa68760db1984f08b2ffbe46f",
            "name": "オイカワ",
            "scientific_name": "Opsariichthys platypus",
            "rank": "species"
        }
    },
    {
        "id": "obs_69548f9a560dc",
        "user_id": "user_69548f9a55ef6",
        "user_name": "木村 健太",
        "user_avatar": "https:\/\/i.pravatar.cc\/150?u=user_69548f9a55ef6",
        "user_rank": "観察者",
        "photos": [
            "uploads\/sample_plant.png"
        ],
        "observed_at": "2025-08-10 05:13:36",
        "created_at": "2025-08-10 05:13:36",
        "lat": 34.63926,
        "lng": 137.72648,
        "cultivation": "wild",
        "note": "大量に発生していました。 #199",
        "status": "Research Grade",
        "taxon": {
            "key": "0263dfb5f7bb8b674cdacc6c04659430",
            "name": "ヒメジョオン",
            "scientific_name": "Erigeron annuus",
            "rank": "species"
        }
    },
    {
        "id": "obs_69548f9a56005",
        "user_id": "user_69548f9a55ef3",
        "user_name": "佐々木 翼",
        "user_avatar": "https:\/\/i.pravatar.cc\/150?u=user_69548f9a55ef3",
        "user_rank": "ビギナー",
        "photos": [
            "uploads\/sample_plant.png"
        ],
        "observed_at": "2025-08-09 10:08:22",
        "created_at": "2025-08-09 10:08:22",
        "lat": 34.74265,
        "lng": 137.77712,
        "cultivation": "wild",
        "note": "これは何でしょうか？ #85",
        "status": "Research Grade",
        "taxon": {
            "key": "0263dfb5f7bb8b674cdacc6c04659430",
            "name": "ヒメジョオン",
            "scientific_name": "Erigeron annuus",
            "rank": "species"
        }
    },
    {
        "id": "obs_69548f9a56032",
        "user_id": "user_69548f9a55eef",
        "user_name": "森 ゆかり",
        "user_avatar": "https:\/\/i.pravatar.cc\/150?u=user_69548f9a55eef",
        "user_rank": "ビギナー",
        "photos": [
            "uploads\/sample_flower.png"
        ],
        "observed_at": "2025-08-07 09:23:42",
        "created_at": "2025-08-07 09:23:42",
        "lat": 34.66304,
        "lng": 137.66992,
        "cultivation": "wild",
        "note": "動きが早かった。 #109",
        "status": "Casual",
        "taxon": {
            "key": "830eeb2309a16036bb6f66b7e1254835",
            "name": "アジサイ",
            "scientific_name": "Hydrangea macrophylla",
            "rank": "species"
        }
    },
    {
        "id": "obs_69548f9a5605c",
        "user_id": "user_69548f9a55eb8",
        "user_name": "阿部 誠",
        "user_avatar": "https:\/\/i.pravatar.cc\/150?u=user_69548f9a55eb8",
        "user_rank": "熟練者",
        "photos": [
            "uploads\/sample_bird.png"
        ],
        "observed_at": "2025-08-07 09:22:16",
        "created_at": "2025-08-07 09:22:16",
        "lat": 34.758919999999996,
        "lng": 137.75130000000001,
        "cultivation": "wild",
        "note": "家の近くです。 #133",
        "status": "Needs ID",
        "taxon": {
            "key": "afa55f620da05840ae2c312e086ada2d",
            "name": "ハシブトガラス",
            "scientific_name": "Corvus macrorhynchos",
            "rank": "species"
        }
    },
    {
        "id": "obs_69548f9a56027",
        "user_id": "user_69548f9a55f07",
        "user_name": "清水 翔太",
        "user_avatar": "https:\/\/i.pravatar.cc\/150?u=user_69548f9a55f07",
        "user_rank": "ビギナー",
        "photos": [
            "uploads\/sample_mammal.png"
        ],
        "observed_at": "2025-08-06 13:07:10",
        "created_at": "2025-08-06 13:07:10",
        "lat": 34.72924,
        "lng": 137.66140000000001,
        "cultivation": "wild",
        "note": "家の近くです。 #102",
        "status": "Casual",
        "taxon": {
            "key": "185e16aa54bbe1758ad39146909e3d26",
            "name": "ノネコ",
            "scientific_name": "Felis catus",
            "rank": "species"
        }
    },
    {
        "id": "obs_69548f9a55fcc",
        "user_id": "user_69548f9a55eef",
        "user_name": "森 ゆかり",
        "user_avatar": "https:\/\/i.pravatar.cc\/150?u=user_69548f9a55eef",
        "user_rank": "ビギナー",
        "photos": [
            "uploads\/sample_bird.png"
        ],
        "observed_at": "2025-08-05 05:09:31",
        "created_at": "2025-08-05 05:09:31",
        "lat": 34.67074,
        "lng": 137.78033,
        "cultivation": "wild",
        "note": " #56",
        "status": "Research Grade",
        "taxon": {
            "key": "afa55f620da05840ae2c312e086ada2d",
            "name": "ハシブトガラス",
            "scientific_name": "Corvus macrorhynchos",
            "rank": "species"
        }
    },
    {
        "id": "obs_69548f9a55ff6",
        "user_id": "user_69548f9a55edd",
        "user_name": "山崎 愛",
        "user_avatar": "https:\/\/i.pravatar.cc\/150?u=user_69548f9a55edd",
        "user_rank": "ビギナー",
        "photos": [
            "uploads\/sample_bird.png"
        ],
        "observed_at": "2025-08-04 03:05:23",
        "created_at": "2025-08-04 03:05:23",
        "lat": 34.6864,
        "lng": 137.70087,
        "cultivation": "wild",
        "note": "大量に発生していました。 #76",
        "status": "Casual",
        "taxon": {
            "key": "cda9814effb1a8067eafc61faf875894",
            "name": "ツバメ",
            "scientific_name": "Hirundo rustica",
            "rank": "species"
        }
    },
    {
        "id": "obs_69548f9a55ff0",
        "user_id": "user_69548f9a55f07",
        "user_name": "清水 翔太",
        "user_avatar": "https:\/\/i.pravatar.cc\/150?u=user_69548f9a55f07",
        "user_rank": "ビギナー",
        "photos": [
            "uploads\/sample_plant.png"
        ],
        "observed_at": "2025-08-03 21:09:01",
        "created_at": "2025-08-03 21:09:01",
        "lat": 34.746719999999996,
        "lng": 137.73195,
        "cultivation": "wild",
        "note": " #72",
        "status": "Research Grade",
        "taxon": {
            "key": "dee7a9982ef45730219e658acb82e7a8",
            "name": "オオバコ",
            "scientific_name": "Plantago asiatica",
            "rank": "species"
        }
    },
    {
        "id": "obs_69548f9a55f2f",
        "user_id": "user_69548f9a55f02",
        "user_name": "石川 崇",
        "user_avatar": "https:\/\/i.pravatar.cc\/150?u=user_69548f9a55f02",
        "user_rank": "ビギナー",
        "photos": [
            "uploads\/sample_insect.png"
        ],
        "observed_at": "2025-08-03 12:13:42",
        "created_at": "2025-08-03 12:13:42",
        "lat": 34.696909999999995,
        "lng": 137.72817,
        "cultivation": "wild",
        "note": "大量に発生していました。 #2",
        "status": "Research Grade",
        "taxon": {
            "key": "890e2525facb93c584dd1e223c8836c4",
            "name": "ナナホシテントウ",
            "scientific_name": "Coccinella septempunctata",
            "rank": "species"
        }
    },
    {
        "id": "obs_69548f9a560ac",
        "user_id": "user_69548f9a55ef3",
        "user_name": "佐々木 翼",
        "user_avatar": "https:\/\/i.pravatar.cc\/150?u=user_69548f9a55ef3",
        "user_rank": "ビギナー",
        "photos": [
            "uploads\/sample_mammal.png"
        ],
        "observed_at": "2025-08-03 11:52:57",
        "created_at": "2025-08-03 11:52:57",
        "lat": 34.74623,
        "lng": 137.68324,
        "cultivation": "wild",
        "note": "家の近くです。 #172",
        "status": "Research Grade",
        "taxon": {
            "key": "b021e922012611f4807f2222eeef54df",
            "name": "タヌキ",
            "scientific_name": "Nyctereutes procyonoides",
            "rank": "species"
        }
    },
    {
        "id": "obs_69548f9a56058",
        "user_id": "user_69548f9a55ef8",
        "user_name": "渡辺 愛",
        "user_avatar": "https:\/\/i.pravatar.cc\/150?u=user_69548f9a55ef8",
        "user_rank": "ビギナー",
        "photos": [
            "uploads\/sample_plant.png"
        ],
        "observed_at": "2025-08-03 07:17:26",
        "created_at": "2025-08-03 07:17:26",
        "lat": 34.71817,
        "lng": 137.79825,
        "cultivation": "wild",
        "note": "家の近くです。 #131",
        "status": "Needs ID",
        "taxon": {
            "key": "dee7a9982ef45730219e658acb82e7a8",
            "name": "オオバコ",
            "scientific_name": "Plantago asiatica",
            "rank": "species"
        }
    },
    {
        "id": "obs_69548f9a56069",
        "user_id": "user_69548f9a55ef0",
        "user_name": "池田 一郎",
        "user_avatar": "https:\/\/i.pravatar.cc\/150?u=user_69548f9a55ef0",
        "user_rank": "ビギナー",
        "photos": [
            "uploads\/sample_mammal.png"
        ],
        "observed_at": "2025-08-02 18:20:39",
        "created_at": "2025-08-02 18:20:39",
        "lat": 34.75747,
        "lng": 137.67978,
        "cultivation": "wild",
        "note": "大量に発生していました。 #140",
        "status": "Research Grade",
        "taxon": {
            "key": "0107d09aca873dfef5fbf7f5daa28f40",
            "name": "アライグマ",
            "scientific_name": "Procyon lotor",
            "rank": "species"
        }
    },
    {
        "id": "obs_69548f9a560bf",
        "user_id": "user_69548f9a55efa",
        "user_name": "松本 陽菜",
        "user_avatar": "https:\/\/i.pravatar.cc\/150?u=user_69548f9a55efa",
        "user_rank": "博士",
        "photos": [
            "uploads\/sample_plant.png"
        ],
        "observed_at": "2025-08-01 00:17:43",
        "created_at": "2025-08-01 00:17:43",
        "lat": 34.79042,
        "lng": 137.65408,
        "cultivation": "wild",
        "note": "動きが早かった。 #182",
        "status": "Research Grade",
        "taxon": {
            "key": "6feb1b534d0a5922785935ca4227b592",
            "name": "シロツメクサ",
            "scientific_name": "Trifolium repens",
            "rank": "species"
        }
    },
    {
        "id": "obs_69548f9a56067",
        "user_id": "user_69548f9a55ed9",
        "user_name": "佐々木 誠",
        "user_avatar": "https:\/\/i.pravatar.cc\/150?u=user_69548f9a55ed9",
        "user_rank": "観察者",
        "photos": [
            "uploads\/sample_insect.png"
        ],
        "observed_at": "2025-08-31 17:38:10",
        "created_at": "2025-08-31 17:38:10",
        "lat": 34.737069999999996,
        "lng": 137.71561,
        "cultivation": "wild",
        "note": "動きが早かった。 #139",
        "status": "Research Grade",
        "taxon": {
            "key": "22247a3c217fe22c007b22e12483b065",
            "name": "モンシロチョウ",
            "scientific_name": "Pieris rapae",
            "rank": "species"
        }
    },
    {
        "id": "obs_69548f9a55fd2",
        "user_id": "user_69548f9a55eee",
        "user_name": "中村 陽菜",
        "user_avatar": "https:\/\/i.pravatar.cc\/150?u=user_69548f9a55eee",
        "user_rank": "ビギナー",
        "photos": [
            "uploads\/sample_mammal.png"
        ],
        "observed_at": "2025-08-31 10:16:27",
        "created_at": "2025-08-31 10:16:27",
        "lat": 34.70405,
        "lng": 137.76706000000001,
        "cultivation": "cultivated",
        "note": "大量に発生していました。 #59",
        "status": "Research Grade",
        "taxon": {
            "key": "0107d09aca873dfef5fbf7f5daa28f40",
            "name": "アライグマ",
            "scientific_name": "Procyon lotor",
            "rank": "species"
        }
    },
    {
        "id": "obs_69548f9a56040",
        "user_id": "user_69548f9a55eda",
        "user_name": "斎藤 葵",
        "user_avatar": "https:\/\/i.pravatar.cc\/150?u=user_69548f9a55eda",
        "user_rank": "観察者",
        "photos": [
            "uploads\/sample_fish.png"
        ],
        "observed_at": "2025-08-30 17:11:31",
        "created_at": "2025-08-30 17:11:31",
        "lat": 34.740719999999996,
        "lng": 137.80204,
        "cultivation": "wild",
        "note": "これは何でしょうか？ #117",
        "status": "Needs ID",
        "taxon": {
            "key": "812b1f2690fb5f898ff7521d9475a5ea",
            "name": "コイ",
            "scientific_name": "Cyprinus carpio",
            "rank": "species"
        }
    },
    {
        "id": "obs_69548f9a55ff2",
        "user_id": "user_69548f9a55ee1",
        "user_name": "中島 大樹",
        "user_avatar": "https:\/\/i.pravatar.cc\/150?u=user_69548f9a55ee1",
        "user_rank": "観察者",
        "photos": [
            "uploads\/sample_insect.png"
        ],
        "observed_at": "2025-08-30 04:23:25",
        "created_at": "2025-08-30 04:23:25",
        "lat": 34.6333,
        "lng": 137.78445,
        "cultivation": "wild",
        "note": "綺麗な色でした。 #73",
        "status": "Needs ID",
        "taxon": {
            "key": "7239cc8b5b5fdbd1ee351ae6ad7807cd",
            "name": "ショウリョウバッタ",
            "scientific_name": "Acrida cinerea",
            "rank": "species"
        }
    },
    {
        "id": "obs_69548f9a5604d",
        "user_id": "user_ya_001",
        "user_name": "八巻 毅",
        "user_avatar": "https:\/\/i.pravatar.cc\/300?u=yamaki",
        "user_rank": "認定研究者",
        "photos": [
            "uploads\/sample_mammal.png"
        ],
        "observed_at": "2025-08-29 09:04:19",
        "created_at": "2025-08-29 09:04:19",
        "lat": 34.64647,
        "lng": 137.7173,
        "cultivation": "wild",
        "note": "これは何でしょうか？ #125",
        "status": "Research Grade",
        "taxon": {
            "key": "91fdc6d57960ec1a1a0e0d9df1e2ab00",
            "name": "ハクビシン",
            "scientific_name": "Paguma larvata",
            "rank": "species"
        }
    },
    {
        "id": "obs_69548f9a55f33",
        "user_id": "user_69548f9a55eb8",
        "user_name": "阿部 誠",
        "user_avatar": "https:\/\/i.pravatar.cc\/150?u=user_69548f9a55eb8",
        "user_rank": "熟練者",
        "photos": [
            "uploads\/sample_mammal.png"
        ],
        "observed_at": "2025-08-28 11:19:24",
        "created_at": "2025-08-28 11:19:24",
        "lat": 34.64214,
        "lng": 137.66222,
        "cultivation": "wild",
        "note": " #3",
        "status": "Needs ID",
        "taxon": {
            "key": "b021e922012611f4807f2222eeef54df",
            "name": "タヌキ",
            "scientific_name": "Nyctereutes procyonoides",
            "rank": "species"
        }
    },
    {
        "id": "obs_69548f9a560d7",
        "user_id": "user_69548f9a55ee6",
        "user_name": "石井 誠",
        "user_avatar": "https:\/\/i.pravatar.cc\/150?u=user_69548f9a55ee6",
        "user_rank": "観察者",
        "photos": [
            "uploads\/sample_insect.png"
        ],
        "observed_at": "2025-08-27 14:38:15",
        "created_at": "2025-08-27 14:38:15",
        "lat": 34.63283,
        "lng": 137.77648,
        "cultivation": "wild",
        "note": "公園で見つけました。 #196",
        "status": "Casual",
        "taxon": {
            "key": "5e8ba5334afd1f8c569b10cb8e694bd2",
            "name": "オニヤンマ",
            "scientific_name": "Anotogaster sieboldii",
            "rank": "species"
        }
    },
    {
        "id": "obs_69548f9a5607e",
        "user_id": "user_69548f9a55ef8",
        "user_name": "渡辺 愛",
        "user_avatar": "https:\/\/i.pravatar.cc\/150?u=user_69548f9a55ef8",
        "user_rank": "ビギナー",
        "photos": [
            "uploads\/sample_fish.png"
        ],
        "observed_at": "2025-08-27 07:27:08",
        "created_at": "2025-08-27 07:27:08",
        "lat": 34.66695,
        "lng": 137.64794,
        "cultivation": "cultivated",
        "note": "公園で見つけました。 #152",
        "status": "Research Grade",
        "taxon": {
            "key": "907e98b5fdcf7000fac6362b543efac6",
            "name": "メダカ",
            "scientific_name": "Oryzias latipes",
            "rank": "species"
        }
    },
    {
        "id": "obs_69548f9a55f53",
        "user_id": "user_69548f9a55f07",
        "user_name": "清水 翔太",
        "user_avatar": "https:\/\/i.pravatar.cc\/150?u=user_69548f9a55f07",
        "user_rank": "ビギナー",
        "photos": [
            "uploads\/sample_flower.png"
        ],
        "observed_at": "2025-08-26 18:33:38",
        "created_at": "2025-08-26 18:33:38",
        "lat": 34.70442,
        "lng": 137.75761,
        "cultivation": "wild",
        "note": "動きが早かった。 #14",
        "status": "Research Grade",
        "taxon": {
            "key": "830eeb2309a16036bb6f66b7e1254835",
            "name": "アジサイ",
            "scientific_name": "Hydrangea macrophylla",
            "rank": "species"
        }
    },
    {
        "id": "obs_69548f9a560b9",
        "user_id": "user_69548f9a55eed",
        "user_name": "小川 健一",
        "user_avatar": "https:\/\/i.pravatar.cc\/150?u=user_69548f9a55eed",
        "user_rank": "観察者",
        "photos": [
            "uploads\/sample_fish.png"
        ],
        "observed_at": "2025-08-26 11:22:04",
        "created_at": "2025-08-26 11:22:04",
        "lat": 34.78853,
        "lng": 137.65712,
        "cultivation": "wild",
        "note": " #178",
        "status": "Needs ID",
        "taxon": {
            "key": "812b1f2690fb5f898ff7521d9475a5ea",
            "name": "コイ",
            "scientific_name": "Cyprinus carpio",
            "rank": "species"
        }
    },
    {
        "id": "obs_69548f9a560cd",
        "user_id": "user_69548f9a55eec",
        "user_name": "山口 三郎",
        "user_avatar": "https:\/\/i.pravatar.cc\/150?u=user_69548f9a55eec",
        "user_rank": "ビギナー",
        "photos": [
            "uploads\/sample_insect.png"
        ],
        "observed_at": "2025-08-23 19:44:17",
        "created_at": "2025-08-23 19:44:17",
        "lat": 34.64163,
        "lng": 137.77605,
        "cultivation": "wild",
        "note": " #190",
        "status": "Research Grade",
        "taxon": {
            "key": "6681e1d7eb8e414ef709c80587416a28",
            "name": "カブトムシ",
            "scientific_name": "Trypoxylus dichotomus",
            "rank": "species"
        }
    },
    {
        "id": "obs_69548f9a55ffc",
        "user_id": "user_69548f9a55ee4",
        "user_name": "中村 翼",
        "user_avatar": "https:\/\/i.pravatar.cc\/150?u=user_69548f9a55ee4",
        "user_rank": "ビギナー",
        "photos": [
            "uploads\/sample_insect.png"
        ],
        "observed_at": "2025-08-23 13:42:05",
        "created_at": "2025-08-23 13:42:05",
        "lat": 34.77664,
        "lng": 137.72849,
        "cultivation": "wild",
        "note": "動きが早かった。 #79",
        "status": "Needs ID",
        "taxon": {
            "key": "890e2525facb93c584dd1e223c8836c4",
            "name": "ナナホシテントウ",
            "scientific_name": "Coccinella septempunctata",
            "rank": "species"
        }
    },
    {
        "id": "obs_69548f9a55fc3",
        "user_id": "user_69548f9a55f07",
        "user_name": "清水 翔太",
        "user_avatar": "https:\/\/i.pravatar.cc\/150?u=user_69548f9a55f07",
        "user_rank": "ビギナー",
        "photos": [
            "uploads\/sample_fish.png"
        ],
        "observed_at": "2025-08-23 00:43:15",
        "created_at": "2025-08-23 00:43:15",
        "lat": 34.68824,
        "lng": 137.68705,
        "cultivation": "wild",
        "note": "初めて見ました！ #53",
        "status": "Research Grade",
        "taxon": {
            "key": "9332a61fa68760db1984f08b2ffbe46f",
            "name": "オイカワ",
            "scientific_name": "Opsariichthys platypus",
            "rank": "species"
        }
    },
    {
        "id": "obs_69548f9a560c1",
        "user_id": "user_69548f9a55ee3",
        "user_name": "林 陽菜",
        "user_avatar": "https:\/\/i.pravatar.cc\/150?u=user_69548f9a55ee3",
        "user_rank": "観察者",
        "photos": [
            "uploads\/sample_flower.png"
        ],
        "observed_at": "2025-08-22 23:31:12",
        "created_at": "2025-08-22 23:31:12",
        "lat": 34.72087,
        "lng": 137.68628,
        "cultivation": "wild",
        "note": " #183",
        "status": "Research Grade",
        "taxon": {
            "key": "aa3561d12b4a04f0a164ea0bd5d3ab90",
            "name": "ヒマワリ",
            "scientific_name": "Helianthus annuus",
            "rank": "species"
        }
    },
    {
        "id": "obs_69548f9a56007",
        "user_id": "user_69548f9a55ede",
        "user_name": "佐々木 智子",
        "user_avatar": "https:\/\/i.pravatar.cc\/150?u=user_69548f9a55ede",
        "user_rank": "観察者",
        "photos": [
            "uploads\/sample_flower.png"
        ],
        "observed_at": "2025-08-22 06:07:58",
        "created_at": "2025-08-22 06:07:58",
        "lat": 34.783809999999995,
        "lng": 137.65519,
        "cultivation": "wild",
        "note": "家の近くです。 #86",
        "status": "Casual",
        "taxon": {
            "key": "aa3561d12b4a04f0a164ea0bd5d3ab90",
            "name": "ヒマワリ",
            "scientific_name": "Helianthus annuus",
            "rank": "species"
        }
    },
    {
        "id": "obs_69548f9a55fd4",
        "user_id": "user_69548f9a55ee1",
        "user_name": "中島 大樹",
        "user_avatar": "https:\/\/i.pravatar.cc\/150?u=user_69548f9a55ee1",
        "user_rank": "観察者",
        "photos": [
            "uploads\/sample_flower.png"
        ],
        "observed_at": "2025-08-22 03:24:57",
        "created_at": "2025-08-22 03:24:57",
        "lat": 34.71822,
        "lng": 137.75412,
        "cultivation": "wild",
        "note": " #60",
        "status": "Research Grade",
        "taxon": {
            "key": "830eeb2309a16036bb6f66b7e1254835",
            "name": "アジサイ",
            "scientific_name": "Hydrangea macrophylla",
            "rank": "species"
        }
    },
    {
        "id": "obs_69548f9a5601c",
        "user_id": "user_69548f9a55edc",
        "user_name": "山田 大樹",
        "user_avatar": "https:\/\/i.pravatar.cc\/150?u=user_69548f9a55edc",
        "user_rank": "認定研究者",
        "photos": [
            "uploads\/sample_plant.png"
        ],
        "observed_at": "2025-08-20 19:50:20",
        "created_at": "2025-08-20 19:50:20",
        "lat": 34.63443,
        "lng": 137.69287,
        "cultivation": "wild",
        "note": " #98",
        "status": "Research Grade",
        "taxon": {
            "key": "68f08be4b2a13127a7454b96a240f4d6",
            "name": "セイヨウタンポポ",
            "scientific_name": "Taraxacum officinale",
            "rank": "species"
        }
    },
    {
        "id": "obs_69548f9a5601a",
        "user_id": "user_69548f9a55edb",
        "user_name": "田中 真由美",
        "user_avatar": "https:\/\/i.pravatar.cc\/150?u=user_69548f9a55edb",
        "user_rank": "認定研究者",
        "photos": [
            "uploads\/sample_flower.png"
        ],
        "observed_at": "2025-08-18 08:23:36",
        "created_at": "2025-08-18 08:23:36",
        "lat": 34.63415,
        "lng": 137.69568,
        "cultivation": "wild",
        "note": " #97",
        "status": "Research Grade",
        "taxon": {
            "key": "aa3561d12b4a04f0a164ea0bd5d3ab90",
            "name": "ヒマワリ",
            "scientific_name": "Helianthus annuus",
            "rank": "species"
        }
    },
    {
        "id": "obs_69548f9a5609e",
        "user_id": "user_69548f9a55ee5",
        "user_name": "林 拓海",
        "user_avatar": "https:\/\/i.pravatar.cc\/150?u=user_69548f9a55ee5",
        "user_rank": "博士",
        "photos": [
            "uploads\/sample_fish.png"
        ],
        "observed_at": "2025-08-17 07:54:48",
        "created_at": "2025-08-17 07:54:48",
        "lat": 34.71245,
        "lng": 137.65987,
        "cultivation": "wild",
        "note": " #163",
        "status": "Research Grade",
        "taxon": {
            "key": "812b1f2690fb5f898ff7521d9475a5ea",
            "name": "コイ",
            "scientific_name": "Cyprinus carpio",
            "rank": "species"
        }
    },
    {
        "id": "obs_69548f9a560db",
        "user_id": "user_69548f9a55edf",
        "user_name": "井上 結衣",
        "user_avatar": "https:\/\/i.pravatar.cc\/150?u=user_69548f9a55edf",
        "user_rank": "観察者",
        "photos": [
            "uploads\/sample_mammal.png"
        ],
        "observed_at": "2025-08-16 13:53:03",
        "created_at": "2025-08-16 13:53:03",
        "lat": 34.657469999999996,
        "lng": 137.74543,
        "cultivation": "wild",
        "note": "動きが早かった。 #198",
        "status": "Needs ID",
        "taxon": {
            "key": "b021e922012611f4807f2222eeef54df",
            "name": "タヌキ",
            "scientific_name": "Nyctereutes procyonoides",
            "rank": "species"
        }
    },
    {
        "id": "obs_69548f9a5603e",
        "user_id": "user_69548f9a55efd",
        "user_name": "阿部 智子",
        "user_avatar": "https:\/\/i.pravatar.cc\/150?u=user_69548f9a55efd",
        "user_rank": "熟練者",
        "photos": [
            "uploads\/sample_mammal.png"
        ],
        "observed_at": "2025-08-14 11:46:06",
        "created_at": "2025-08-14 11:46:06",
        "lat": 34.72483,
        "lng": 137.79575,
        "cultivation": "wild",
        "note": "綺麗な色でした。 #116",
        "status": "Needs ID",
        "taxon": {
            "key": "b021e922012611f4807f2222eeef54df",
            "name": "タヌキ",
            "scientific_name": "Nyctereutes procyonoides",
            "rank": "species"
        }
    },
    {
        "id": "obs_69548f9a55f59",
        "user_id": "user_69548f9a55efb",
        "user_name": "中島 花子",
        "user_avatar": "https:\/\/i.pravatar.cc\/150?u=user_69548f9a55efb",
        "user_rank": "観察者",
        "photos": [
            "uploads\/sample_insect.png"
        ],
        "observed_at": "2025-08-14 06:36:21",
        "created_at": "2025-08-14 06:36:21",
        "lat": 34.71212,
        "lng": 137.76291,
        "cultivation": "wild",
        "note": "大量に発生していました。 #17",
        "status": "Needs ID",
        "taxon": {
            "key": "22247a3c217fe22c007b22e12483b065",
            "name": "モンシロチョウ",
            "scientific_name": "Pieris rapae",
            "rank": "species"
        }
    },
    {
        "id": "obs_69548f9a56088",
        "user_id": "user_69548f9a55efd",
        "user_name": "阿部 智子",
        "user_avatar": "https:\/\/i.pravatar.cc\/150?u=user_69548f9a55efd",
        "user_rank": "熟練者",
        "photos": [
            "uploads\/sample_bird.png"
        ],
        "observed_at": "2025-08-13 17:33:26",
        "created_at": "2025-08-13 17:33:26",
        "lat": 34.68712,
        "lng": 137.69963,
        "cultivation": "wild",
        "note": "大量に発生していました。 #157",
        "status": "Research Grade",
        "taxon": {
            "key": "5c6614249f02d9e594d3fd4b98278592",
            "name": "スズメ",
            "scientific_name": "Passer montanus",
            "rank": "species"
        }
    },
    {
        "id": "obs_69548f9a55f92",
        "user_id": "user_69548f9a55eda",
        "user_name": "斎藤 葵",
        "user_avatar": "https:\/\/i.pravatar.cc\/150?u=user_69548f9a55eda",
        "user_rank": "観察者",
        "photos": [
            "uploads\/sample_fish.png"
        ],
        "observed_at": "2025-08-11 07:55:47",
        "created_at": "2025-08-11 07:55:47",
        "lat": 34.68204,
        "lng": 137.73687,
        "cultivation": "wild",
        "note": "これは何でしょうか？ #40",
        "status": "Research Grade",
        "taxon": {
            "key": "9332a61fa68760db1984f08b2ffbe46f",
            "name": "オイカワ",
            "scientific_name": "Opsariichthys platypus",
            "rank": "species"
        }
    },
    {
        "id": "obs_69548f9a560dc",
        "user_id": "user_69548f9a55ef6",
        "user_name": "木村 健太",
        "user_avatar": "https:\/\/i.pravatar.cc\/150?u=user_69548f9a55ef6",
        "user_rank": "観察者",
        "photos": [
            "uploads\/sample_plant.png"
        ],
        "observed_at": "2025-08-10 05:13:36",
        "created_at": "2025-08-10 05:13:36",
        "lat": 34.63926,
        "lng": 137.72648,
        "cultivation": "wild",
        "note": "大量に発生していました。 #199",
        "status": "Research Grade",
        "taxon": {
            "key": "0263dfb5f7bb8b674cdacc6c04659430",
            "name": "ヒメジョオン",
            "scientific_name": "Erigeron annuus",
            "rank": "species"
        }
    },
    {
        "id": "obs_69548f9a56005",
        "user_id": "user_69548f9a55ef3",
        "user_name": "佐々木 翼",
        "user_avatar": "https:\/\/i.pravatar.cc\/150?u=user_69548f9a55ef3",
        "user_rank": "ビギナー",
        "photos": [
            "uploads\/sample_plant.png"
        ],
        "observed_at": "2025-08-09 10:08:22",
        "created_at": "2025-08-09 10:08:22",
        "lat": 34.74265,
        "lng": 137.77712,
        "cultivation": "wild",
        "note": "これは何でしょうか？ #85",
        "status": "Research Grade",
        "taxon": {
            "key": "0263dfb5f7bb8b674cdacc6c04659430",
            "name": "ヒメジョオン",
            "scientific_name": "Erigeron annuus",
            "rank": "species"
        }
    },
    {
        "id": "obs_69548f9a56032",
        "user_id": "user_69548f9a55eef",
        "user_name": "森 ゆかり",
        "user_avatar": "https:\/\/i.pravatar.cc\/150?u=user_69548f9a55eef",
        "user_rank": "ビギナー",
        "photos": [
            "uploads\/sample_flower.png"
        ],
        "observed_at": "2025-08-07 09:23:42",
        "created_at": "2025-08-07 09:23:42",
        "lat": 34.66304,
        "lng": 137.66992,
        "cultivation": "wild",
        "note": "動きが早かった。 #109",
        "status": "Casual",
        "taxon": {
            "key": "830eeb2309a16036bb6f66b7e1254835",
            "name": "アジサイ",
            "scientific_name": "Hydrangea macrophylla",
            "rank": "species"
        }
    },
    {
        "id": "obs_69548f9a5605c",
        "user_id": "user_69548f9a55eb8",
        "user_name": "阿部 誠",
        "user_avatar": "https:\/\/i.pravatar.cc\/150?u=user_69548f9a55eb8",
        "user_rank": "熟練者",
        "photos": [
            "uploads\/sample_bird.png"
        ],
        "observed_at": "2025-08-07 09:22:16",
        "created_at": "2025-08-07 09:22:16",
        "lat": 34.758919999999996,
        "lng": 137.75130000000001,
        "cultivation": "wild",
        "note": "家の近くです。 #133",
        "status": "Needs ID",
        "taxon": {
            "key": "afa55f620da05840ae2c312e086ada2d",
            "name": "ハシブトガラス",
            "scientific_name": "Corvus macrorhynchos",
            "rank": "species"
        }
    },
    {
        "id": "obs_69548f9a56027",
        "user_id": "user_69548f9a55f07",
        "user_name": "清水 翔太",
        "user_avatar": "https:\/\/i.pravatar.cc\/150?u=user_69548f9a55f07",
        "user_rank": "ビギナー",
        "photos": [
            "uploads\/sample_mammal.png"
        ],
        "observed_at": "2025-08-06 13:07:10",
        "created_at": "2025-08-06 13:07:10",
        "lat": 34.72924,
        "lng": 137.66140000000001,
        "cultivation": "wild",
        "note": "家の近くです。 #102",
        "status": "Casual",
        "taxon": {
            "key": "185e16aa54bbe1758ad39146909e3d26",
            "name": "ノネコ",
            "scientific_name": "Felis catus",
            "rank": "species"
        }
    },
    {
        "id": "obs_69548f9a55fcc",
        "user_id": "user_69548f9a55eef",
        "user_name": "森 ゆかり",
        "user_avatar": "https:\/\/i.pravatar.cc\/150?u=user_69548f9a55eef",
        "user_rank": "ビギナー",
        "photos": [
            "uploads\/sample_bird.png"
        ],
        "observed_at": "2025-08-05 05:09:31",
        "created_at": "2025-08-05 05:09:31",
        "lat": 34.67074,
        "lng": 137.78033,
        "cultivation": "wild",
        "note": " #56",
        "status": "Research Grade",
        "taxon": {
            "key": "afa55f620da05840ae2c312e086ada2d",
            "name": "ハシブトガラス",
            "scientific_name": "Corvus macrorhynchos",
            "rank": "species"
        }
    },
    {
        "id": "obs_69548f9a55ff6",
        "user_id": "user_69548f9a55edd",
        "user_name": "山崎 愛",
        "user_avatar": "https:\/\/i.pravatar.cc\/150?u=user_69548f9a55edd",
        "user_rank": "ビギナー",
        "photos": [
            "uploads\/sample_bird.png"
        ],
        "observed_at": "2025-08-04 03:05:23",
        "created_at": "2025-08-04 03:05:23",
        "lat": 34.6864,
        "lng": 137.70087,
        "cultivation": "wild",
        "note": "大量に発生していました。 #76",
        "status": "Casual",
        "taxon": {
            "key": "cda9814effb1a8067eafc61faf875894",
            "name": "ツバメ",
            "scientific_name": "Hirundo rustica",
            "rank": "species"
        }
    },
    {
        "id": "obs_69548f9a55ff0",
        "user_id": "user_69548f9a55f07",
        "user_name": "清水 翔太",
        "user_avatar": "https:\/\/i.pravatar.cc\/150?u=user_69548f9a55f07",
        "user_rank": "ビギナー",
        "photos": [
            "uploads\/sample_plant.png"
        ],
        "observed_at": "2025-08-03 21:09:01",
        "created_at": "2025-08-03 21:09:01",
        "lat": 34.746719999999996,
        "lng": 137.73195,
        "cultivation": "wild",
        "note": " #72",
        "status": "Research Grade",
        "taxon": {
            "key": "dee7a9982ef45730219e658acb82e7a8",
            "name": "オオバコ",
            "scientific_name": "Plantago asiatica",
            "rank": "species"
        }
    },
    {
        "id": "obs_69548f9a55f2f",
        "user_id": "user_69548f9a55f02",
        "user_name": "石川 崇",
        "user_avatar": "https:\/\/i.pravatar.cc\/150?u=user_69548f9a55f02",
        "user_rank": "ビギナー",
        "photos": [
            "uploads\/sample_insect.png"
        ],
        "observed_at": "2025-08-03 12:13:42",
        "created_at": "2025-08-03 12:13:42",
        "lat": 34.696909999999995,
        "lng": 137.72817,
        "cultivation": "wild",
        "note": "大量に発生していました。 #2",
        "status": "Research Grade",
        "taxon": {
            "key": "890e2525facb93c584dd1e223c8836c4",
            "name": "ナナホシテントウ",
            "scientific_name": "Coccinella septempunctata",
            "rank": "species"
        }
    },
    {
        "id": "obs_69548f9a560ac",
        "user_id": "user_69548f9a55ef3",
        "user_name": "佐々木 翼",
        "user_avatar": "https:\/\/i.pravatar.cc\/150?u=user_69548f9a55ef3",
        "user_rank": "ビギナー",
        "photos": [
            "uploads\/sample_mammal.png"
        ],
        "observed_at": "2025-08-03 11:52:57",
        "created_at": "2025-08-03 11:52:57",
        "lat": 34.74623,
        "lng": 137.68324,
        "cultivation": "wild",
        "note": "家の近くです。 #172",
        "status": "Research Grade",
        "taxon": {
            "key": "b021e922012611f4807f2222eeef54df",
            "name": "タヌキ",
            "scientific_name": "Nyctereutes procyonoides",
            "rank": "species"
        }
    },
    {
        "id": "obs_69548f9a56058",
        "user_id": "user_69548f9a55ef8",
        "user_name": "渡辺 愛",
        "user_avatar": "https:\/\/i.pravatar.cc\/150?u=user_69548f9a55ef8",
        "user_rank": "ビギナー",
        "photos": [
            "uploads\/sample_plant.png"
        ],
        "observed_at": "2025-08-03 07:17:26",
        "created_at": "2025-08-03 07:17:26",
        "lat": 34.71817,
        "lng": 137.79825,
        "cultivation": "wild",
        "note": "家の近くです。 #131",
        "status": "Needs ID",
        "taxon": {
            "key": "dee7a9982ef45730219e658acb82e7a8",
            "name": "オオバコ",
            "scientific_name": "Plantago asiatica",
            "rank": "species"
        }
    },
    {
        "id": "obs_69548f9a56069",
        "user_id": "user_69548f9a55ef0",
        "user_name": "池田 一郎",
        "user_avatar": "https:\/\/i.pravatar.cc\/150?u=user_69548f9a55ef0",
        "user_rank": "ビギナー",
        "photos": [
            "uploads\/sample_mammal.png"
        ],
        "observed_at": "2025-08-02 18:20:39",
        "created_at": "2025-08-02 18:20:39",
        "lat": 34.75747,
        "lng": 137.67978,
        "cultivation": "wild",
        "note": "大量に発生していました。 #140",
        "status": "Research Grade",
        "taxon": {
            "key": "0107d09aca873dfef5fbf7f5daa28f40",
            "name": "アライグマ",
            "scientific_name": "Procyon lotor",
            "rank": "species"
        }
    },
    {
        "id": "obs_69548f9a560bf",
        "user_id": "user_69548f9a55efa",
        "user_name": "松本 陽菜",
        "user_avatar": "https:\/\/i.pravatar.cc\/150?u=user_69548f9a55efa",
        "user_rank": "博士",
        "photos": [
            "uploads\/sample_plant.png"
        ],
        "observed_at": "2025-08-01 00:17:43",
        "created_at": "2025-08-01 00:17:43",
        "lat": 34.79042,
        "lng": 137.65408,
        "cultivation": "wild",
        "note": "動きが早かった。 #182",
        "status": "Research Grade",
        "taxon": {
            "key": "6feb1b534d0a5922785935ca4227b592",
            "name": "シロツメクサ",
            "scientific_name": "Trifolium repens",
            "rank": "species"
        }
    }
]